{
"meta":{"test_sets":[],"test_metrics":[],"learn_metrics":[{"best_value":"Min","name":"Logloss"}],"launch_mode":"Train","parameters":"","iteration_count":1000,"learn_sets":["learn"],"name":"experiment"},
"iterations":[
{"learn":[0.6726186708],"iteration":0,"passed_time":0.04338477538,"remaining_time":43.3413906},
{"learn":[0.6536523021],"iteration":1,"passed_time":0.08611681589,"remaining_time":42.97229113},
{"learn":[0.6377057597],"iteration":2,"passed_time":0.1661135953,"remaining_time":55.20508483},
{"learn":[0.6239677095],"iteration":3,"passed_time":0.18365159,"remaining_time":45.72924591},
{"learn":[0.6087727564],"iteration":4,"passed_time":0.2072284947,"remaining_time":41.23847044},
{"learn":[0.5921843132],"iteration":5,"passed_time":0.2235102908,"remaining_time":37.02820484},
{"learn":[0.576888163],"iteration":6,"passed_time":0.2487066228,"remaining_time":35.28081093},
{"learn":[0.5644644092],"iteration":7,"passed_time":0.2691417716,"remaining_time":33.37357968},
{"learn":[0.5517164819],"iteration":8,"passed_time":0.2972319414,"remaining_time":32.72853932},
{"learn":[0.5399688549],"iteration":9,"passed_time":0.3228583363,"remaining_time":31.9629753},
{"learn":[0.5284613018],"iteration":10,"passed_time":0.3491310231,"remaining_time":31.39005289},
{"learn":[0.5190000467],"iteration":11,"passed_time":0.4117136858,"remaining_time":33.89776013},
{"learn":[0.5092472806],"iteration":12,"passed_time":0.4334765473,"remaining_time":32.91087325},
{"learn":[0.499779798],"iteration":13,"passed_time":0.4665932417,"remaining_time":32.86149545},
{"learn":[0.4916040886],"iteration":14,"passed_time":0.4865891372,"remaining_time":31.95268667},
{"learn":[0.4828572104],"iteration":15,"passed_time":0.4966420723,"remaining_time":30.54348745},
{"learn":[0.4754392108],"iteration":16,"passed_time":0.5390442921,"remaining_time":31.16944348},
{"learn":[0.4680478664],"iteration":17,"passed_time":0.5703528465,"remaining_time":31.1159164},
{"learn":[0.4617536271],"iteration":18,"passed_time":0.5907090911,"remaining_time":30.49924307},
{"learn":[0.4537437868],"iteration":19,"passed_time":0.6102746214,"remaining_time":29.90345645},
{"learn":[0.4475319766],"iteration":20,"passed_time":0.6279069767,"remaining_time":29.27242525},
{"learn":[0.4420175398],"iteration":21,"passed_time":0.6642289483,"remaining_time":29.52799597},
{"learn":[0.4367072798],"iteration":22,"passed_time":0.6802357685,"remaining_time":28.89523243},
{"learn":[0.4319384653],"iteration":23,"passed_time":0.7063033081,"remaining_time":28.7230012},
{"learn":[0.427368049],"iteration":24,"passed_time":0.7713535717,"remaining_time":30.0827893},
{"learn":[0.4227675957],"iteration":25,"passed_time":0.7913849409,"remaining_time":29.6464974},
{"learn":[0.4178857969],"iteration":26,"passed_time":0.8127408662,"remaining_time":29.2887727},
{"learn":[0.4132877041],"iteration":27,"passed_time":0.8401669601,"remaining_time":29.1657959},
{"learn":[0.4091251941],"iteration":28,"passed_time":0.8485565576,"remaining_time":28.41201439},
{"learn":[0.4051490764],"iteration":29,"passed_time":0.8620514638,"remaining_time":27.87299733},
{"learn":[0.4008149623],"iteration":30,"passed_time":0.8935484424,"remaining_time":27.93059486},
{"learn":[0.3972441394],"iteration":31,"passed_time":0.925164956,"remaining_time":27.98623992},
{"learn":[0.3935919325],"iteration":32,"passed_time":0.9529589969,"remaining_time":27.92458637},
{"learn":[0.3911613829],"iteration":33,"passed_time":1.007893561,"remaining_time":28.63603472},
{"learn":[0.3878840018],"iteration":34,"passed_time":1.054658377,"remaining_time":29.07843811},
{"learn":[0.3854463852],"iteration":35,"passed_time":1.118709689,"remaining_time":29.95655946},
{"learn":[0.3825406202],"iteration":36,"passed_time":1.146723294,"remaining_time":29.84579817},
{"learn":[0.3796115579],"iteration":37,"passed_time":1.188770827,"remaining_time":30.09467199},
{"learn":[0.3761443469],"iteration":38,"passed_time":1.22065269,"remaining_time":30.07813424},
{"learn":[0.3738651895],"iteration":39,"passed_time":1.261720835,"remaining_time":30.28130004},
{"learn":[0.3714181722],"iteration":40,"passed_time":1.289504633,"remaining_time":30.16182788},
{"learn":[0.3686190597],"iteration":41,"passed_time":1.309541142,"remaining_time":29.87000986},
{"learn":[0.366020919],"iteration":42,"passed_time":1.318839126,"remaining_time":29.35183822},
{"learn":[0.3645333032],"iteration":43,"passed_time":1.336043157,"remaining_time":29.02857405},
{"learn":[0.36249733],"iteration":44,"passed_time":1.344228032,"remaining_time":28.52750601},
{"learn":[0.3601019947],"iteration":45,"passed_time":1.355271199,"remaining_time":28.10714616},
{"learn":[0.3588884766],"iteration":46,"passed_time":1.36345686,"remaining_time":27.64626357},
{"learn":[0.3575406066],"iteration":47,"passed_time":1.372425438,"remaining_time":27.21977119},
{"learn":[0.3559931672],"iteration":48,"passed_time":1.380336725,"remaining_time":26.78980052},
{"learn":[0.3543726942],"iteration":49,"passed_time":1.388718886,"remaining_time":26.38565884},
{"learn":[0.3529405722],"iteration":50,"passed_time":1.395764858,"remaining_time":25.97217353},
{"learn":[0.3511737905],"iteration":51,"passed_time":1.404188428,"remaining_time":25.59943518},
{"learn":[0.3501873391],"iteration":52,"passed_time":1.412304385,"remaining_time":25.23494816},
{"learn":[0.3488999515],"iteration":53,"passed_time":1.420846955,"remaining_time":24.8911337},
{"learn":[0.3477367559],"iteration":54,"passed_time":1.42831819,"remaining_time":24.54110345},
{"learn":[0.3467782497],"iteration":55,"passed_time":1.435468623,"remaining_time":24.19789965},
{"learn":[0.3457463055],"iteration":56,"passed_time":1.442098121,"remaining_time":23.85786891},
{"learn":[0.3443119127],"iteration":57,"passed_time":1.449171401,"remaining_time":23.53654241},
{"learn":[0.3432252795],"iteration":58,"passed_time":1.456546767,"remaining_time":23.23068657},
{"learn":[0.3416553223],"iteration":59,"passed_time":1.463798673,"remaining_time":22.93284588},
{"learn":[0.340455836],"iteration":60,"passed_time":1.47158542,"remaining_time":22.65276573},
{"learn":[0.3388176456],"iteration":61,"passed_time":1.479941995,"remaining_time":22.39009018},
{"learn":[0.3375826265],"iteration":62,"passed_time":1.488240648,"remaining_time":22.13462678},
{"learn":[0.3360260667],"iteration":63,"passed_time":1.497090052,"remaining_time":21.89494201},
{"learn":[0.3350481176],"iteration":64,"passed_time":1.504670119,"remaining_time":21.64410094},
{"learn":[0.3342777503],"iteration":65,"passed_time":1.513629348,"remaining_time":21.42014865},
{"learn":[0.3331359643],"iteration":66,"passed_time":1.521268225,"remaining_time":21.18422767},
{"learn":[0.3317650794],"iteration":67,"passed_time":1.528388715,"remaining_time":20.94791592},
{"learn":[0.3305066034],"iteration":68,"passed_time":1.536221698,"remaining_time":20.72786088},
{"learn":[0.3298967205],"iteration":69,"passed_time":1.543603641,"remaining_time":20.50787695},
{"learn":[0.329090133],"iteration":70,"passed_time":1.551040026,"remaining_time":20.29459415},
{"learn":[0.3283491315],"iteration":71,"passed_time":1.558283823,"remaining_time":20.08454706},
{"learn":[0.3274999896],"iteration":72,"passed_time":1.566480537,"remaining_time":19.89215696},
{"learn":[0.3268139587],"iteration":73,"passed_time":1.573882943,"remaining_time":19.69480547},
{"learn":[0.3260571658],"iteration":74,"passed_time":1.581564387,"remaining_time":19.50596077},
{"learn":[0.3249786252],"iteration":75,"passed_time":1.58887843,"remaining_time":19.3174167},
{"learn":[0.324485236],"iteration":76,"passed_time":1.597421618,"remaining_time":19.14831368},
{"learn":[0.3239786595],"iteration":77,"passed_time":1.604566872,"remaining_time":18.96680328},
{"learn":[0.3231240683],"iteration":78,"passed_time":1.612357005,"remaining_time":18.79722533},
{"learn":[0.3222759361],"iteration":79,"passed_time":1.619585228,"remaining_time":18.62523012},
{"learn":[0.322027514],"iteration":80,"passed_time":1.628148847,"remaining_time":18.4724542},
{"learn":[0.3215679153],"iteration":81,"passed_time":1.635349414,"remaining_time":18.30793612},
{"learn":[0.3208874301],"iteration":82,"passed_time":1.642737163,"remaining_time":18.14927685},
{"learn":[0.3202691601],"iteration":83,"passed_time":1.649686329,"remaining_time":17.98943663},
{"learn":[0.3196188955],"iteration":84,"passed_time":1.657076862,"remaining_time":17.83794504},
{"learn":[0.318916186],"iteration":85,"passed_time":1.664127249,"remaining_time":17.6861896},
{"learn":[0.3179351125],"iteration":86,"passed_time":1.671535153,"remaining_time":17.54151259},
{"learn":[0.3175538886],"iteration":87,"passed_time":1.678607161,"remaining_time":17.39647421},
{"learn":[0.3170666455],"iteration":88,"passed_time":1.685500945,"remaining_time":17.25271192},
{"learn":[0.3165078464],"iteration":89,"passed_time":1.69297,"remaining_time":17.11780778},
{"learn":[0.3159563511],"iteration":90,"passed_time":1.699658525,"remaining_time":16.97790768},
{"learn":[0.3156101762],"iteration":91,"passed_time":1.729199485,"remaining_time":17.06644709},
{"learn":[0.3148998213],"iteration":92,"passed_time":1.751298319,"remaining_time":17.0798664},
{"learn":[0.3146619488],"iteration":93,"passed_time":1.783287165,"remaining_time":17.18785289},
{"learn":[0.3138843768],"iteration":94,"passed_time":1.809446193,"remaining_time":17.23735583},
{"learn":[0.3133482426],"iteration":95,"passed_time":1.821821737,"remaining_time":17.15548802},
{"learn":[0.3129109732],"iteration":96,"passed_time":1.83156074,"remaining_time":17.05050874},
{"learn":[0.3120896113],"iteration":97,"passed_time":1.859376502,"remaining_time":17.11385311},
{"learn":[0.3115909562],"iteration":98,"passed_time":1.882729545,"remaining_time":17.13474061},
{"learn":[0.3111088411],"iteration":99,"passed_time":1.901558915,"remaining_time":17.11403023},
{"learn":[0.3107275514],"iteration":100,"passed_time":1.918975817,"remaining_time":17.08078474},
{"learn":[0.3105739431],"iteration":101,"passed_time":1.943397224,"remaining_time":17.10951674},
{"learn":[0.3100801898],"iteration":102,"passed_time":1.978883317,"remaining_time":17.23357607},
{"learn":[0.3093645569],"iteration":103,"passed_time":1.98938914,"remaining_time":17.13935259},
{"learn":[0.3088845515],"iteration":104,"passed_time":1.998789702,"remaining_time":17.0373027},
{"learn":[0.3083704522],"iteration":105,"passed_time":2.010585641,"remaining_time":16.95720343},
{"learn":[0.3078262357],"iteration":106,"passed_time":2.025073807,"remaining_time":16.90084962},
{"learn":[0.3072953614],"iteration":107,"passed_time":2.03607077,"remaining_time":16.81643636},
{"learn":[0.3070280872],"iteration":108,"passed_time":2.053881204,"remaining_time":16.78906562},
{"learn":[0.3067033908],"iteration":109,"passed_time":2.081080076,"remaining_time":16.8378297},
{"learn":[0.3063521361],"iteration":110,"passed_time":2.09371163,"remaining_time":16.76855531},
{"learn":[0.3059394035],"iteration":111,"passed_time":2.104506629,"remaining_time":16.68573113},
{"learn":[0.3054845632],"iteration":112,"passed_time":2.114689693,"remaining_time":16.59937838},
{"learn":[0.3050812629],"iteration":113,"passed_time":2.15754358,"remaining_time":16.7682773},
{"learn":[0.3046029468],"iteration":114,"passed_time":2.166610164,"remaining_time":16.67347822},
{"learn":[0.3043249451],"iteration":115,"passed_time":2.17534154,"remaining_time":16.57760277},
{"learn":[0.3040268618],"iteration":116,"passed_time":2.202516801,"remaining_time":16.62241312},
{"learn":[0.3036084627],"iteration":117,"passed_time":2.21131214,"remaining_time":16.52862125},
{"learn":[0.3032210136],"iteration":118,"passed_time":2.232349622,"remaining_time":16.5268909},
{"learn":[0.3029435909],"iteration":119,"passed_time":2.250078235,"remaining_time":16.50057372},
{"learn":[0.3027869499],"iteration":120,"passed_time":2.265379802,"remaining_time":16.45676732},
{"learn":[0.3026366319],"iteration":121,"passed_time":2.286675726,"remaining_time":16.45656793},
{"learn":[0.3021176262],"iteration":122,"passed_time":2.326683102,"remaining_time":16.58943968},
{"learn":[0.3018889087],"iteration":123,"passed_time":2.343306419,"remaining_time":16.55432599},
{"learn":[0.3014900495],"iteration":124,"passed_time":2.361176333,"remaining_time":16.52823433},
{"learn":[0.3012068075],"iteration":125,"passed_time":2.380342144,"remaining_time":16.51126217},
{"learn":[0.3008298582],"iteration":126,"passed_time":2.392469079,"remaining_time":16.44587012},
{"learn":[0.3006581343],"iteration":127,"passed_time":2.407638425,"remaining_time":16.40203677},
{"learn":[0.3004782221],"iteration":128,"passed_time":2.429758589,"remaining_time":16.40557931},
{"learn":[0.3000914673],"iteration":129,"passed_time":2.453048082,"remaining_time":16.41655255},
{"learn":[0.2997677369],"iteration":130,"passed_time":2.476228673,"remaining_time":16.42628028},
{"learn":[0.2993796535],"iteration":131,"passed_time":2.491985195,"remaining_time":16.38669052},
{"learn":[0.2991611767],"iteration":132,"passed_time":2.557426374,"remaining_time":16.67134335},
{"learn":[0.2990589376],"iteration":133,"passed_time":2.570735287,"remaining_time":16.6138564},
{"learn":[0.2987849273],"iteration":134,"passed_time":2.596459828,"remaining_time":16.63657594},
{"learn":[0.2985284638],"iteration":135,"passed_time":2.638934305,"remaining_time":16.76499441},
{"learn":[0.2982884388],"iteration":136,"passed_time":2.700300061,"remaining_time":17.00991936},
{"learn":[0.2979819731],"iteration":137,"passed_time":2.727550286,"remaining_time":17.03730686},
{"learn":[0.2978665849],"iteration":138,"passed_time":2.736403348,"remaining_time":16.94995168},
{"learn":[0.2974680056],"iteration":139,"passed_time":2.75625391,"remaining_time":16.93127402},
{"learn":[0.2972329461],"iteration":140,"passed_time":2.775422312,"remaining_time":16.90842388},
{"learn":[0.2969267976],"iteration":141,"passed_time":2.787343331,"remaining_time":16.84183506},
{"learn":[0.2967329076],"iteration":142,"passed_time":2.79607153,"remaining_time":16.75687623},
{"learn":[0.296435254],"iteration":143,"passed_time":2.807455572,"remaining_time":16.68876368},
{"learn":[0.2960966195],"iteration":144,"passed_time":2.830189034,"remaining_time":16.68835603},
{"learn":[0.2959367383],"iteration":145,"passed_time":2.915074667,"remaining_time":17.05119018},
{"learn":[0.2956699646],"iteration":146,"passed_time":2.938262281,"remaining_time":17.0499165},
{"learn":[0.2954333284],"iteration":147,"passed_time":2.987304719,"remaining_time":17.19718663},
{"learn":[0.2950715377],"iteration":148,"passed_time":3.007194633,"remaining_time":17.17531968},
{"learn":[0.2947754962],"iteration":149,"passed_time":3.031059128,"remaining_time":17.17600173},
{"learn":[0.2946332092],"iteration":150,"passed_time":3.040439856,"remaining_time":17.09492343},
{"learn":[0.2944157485],"iteration":151,"passed_time":3.052231265,"remaining_time":17.02823758},
{"learn":[0.2942652079],"iteration":152,"passed_time":3.060875496,"remaining_time":16.9448467},
{"learn":[0.2941380677],"iteration":153,"passed_time":3.072100195,"remaining_time":16.87660237},
{"learn":[0.2938904361],"iteration":154,"passed_time":3.080160158,"remaining_time":16.79184086},
{"learn":[0.2937285572],"iteration":155,"passed_time":3.088477968,"remaining_time":16.70945772},
{"learn":[0.2934951225],"iteration":156,"passed_time":3.096033388,"remaining_time":16.6239245},
{"learn":[0.2933455315],"iteration":157,"passed_time":3.105313722,"remaining_time":16.54857059},
{"learn":[0.29319027],"iteration":158,"passed_time":3.113700496,"remaining_time":16.46932149},
{"learn":[0.2928138932],"iteration":159,"passed_time":3.12202848,"remaining_time":16.39064952},
{"learn":[0.2926865261],"iteration":160,"passed_time":3.129785811,"remaining_time":16.30987761},
{"learn":[0.2925131449],"iteration":161,"passed_time":3.136945874,"remaining_time":16.22691755},
{"learn":[0.2923444869],"iteration":162,"passed_time":3.145282956,"remaining_time":16.1509315},
{"learn":[0.2921017583],"iteration":163,"passed_time":3.153662468,"remaining_time":16.07598673},
{"learn":[0.2919299491],"iteration":164,"passed_time":3.161210576,"remaining_time":15.9976414},
{"learn":[0.2917261968],"iteration":165,"passed_time":3.170991,"remaining_time":15.93136442},
{"learn":[0.2915476077],"iteration":166,"passed_time":3.179438618,"remaining_time":15.85911598},
{"learn":[0.2912669732],"iteration":167,"passed_time":3.188007208,"remaining_time":15.78822617},
{"learn":[0.2911130347],"iteration":168,"passed_time":3.195878763,"remaining_time":15.71464646},
{"learn":[0.2909558806],"iteration":169,"passed_time":3.205060935,"remaining_time":15.64823868},
{"learn":[0.2908636122],"iteration":170,"passed_time":3.213645192,"remaining_time":15.57960155},
{"learn":[0.2906690496],"iteration":171,"passed_time":3.221648026,"remaining_time":15.50886376},
{"learn":[0.2905285504],"iteration":172,"passed_time":3.229359258,"remaining_time":15.43745726},
{"learn":[0.2902921277],"iteration":173,"passed_time":3.237884122,"remaining_time":15.37064531},
{"learn":[0.2901348933],"iteration":174,"passed_time":3.246375241,"remaining_time":15.30434042},
{"learn":[0.2899469754],"iteration":175,"passed_time":3.253261569,"remaining_time":15.23117916},
{"learn":[0.2897048638],"iteration":176,"passed_time":3.260206894,"remaining_time":15.15904109},
{"learn":[0.2895943594],"iteration":177,"passed_time":3.267883717,"remaining_time":15.09101357},
{"learn":[0.2893258847],"iteration":178,"passed_time":3.274630481,"remaining_time":15.01939455},
{"learn":[0.2891732182],"iteration":179,"passed_time":3.282734916,"remaining_time":14.95468128},
{"learn":[0.2890817669],"iteration":180,"passed_time":3.289868347,"remaining_time":14.88619987},
{"learn":[0.2889748435],"iteration":181,"passed_time":3.297774695,"remaining_time":14.82186649},
{"learn":[0.2886946734],"iteration":182,"passed_time":3.305633709,"remaining_time":14.75793847},
{"learn":[0.2885306381],"iteration":183,"passed_time":3.313741805,"remaining_time":14.69572453},
{"learn":[0.2883826628],"iteration":184,"passed_time":3.320888871,"remaining_time":14.62986178},
{"learn":[0.2882323884],"iteration":185,"passed_time":3.328480704,"remaining_time":14.56657685},
{"learn":[0.2880800256],"iteration":186,"passed_time":3.335752569,"remaining_time":14.50249646},
{"learn":[0.288000191],"iteration":187,"passed_time":3.343213848,"remaining_time":14.43983854},
{"learn":[0.2879004921],"iteration":188,"passed_time":3.35066709,"remaining_time":14.37773021},
{"learn":[0.2878160504],"iteration":189,"passed_time":3.358587485,"remaining_time":14.31818875},
{"learn":[0.2876677501],"iteration":190,"passed_time":3.365740697,"remaining_time":14.25593835},
{"learn":[0.2873817752],"iteration":191,"passed_time":3.373500322,"remaining_time":14.19681385},
{"learn":[0.2871818312],"iteration":192,"passed_time":3.385985277,"remaining_time":14.15797989},
{"learn":[0.2870354583],"iteration":193,"passed_time":3.39560354,"remaining_time":14.10750749},
{"learn":[0.286881961],"iteration":194,"passed_time":3.404152186,"remaining_time":14.05303851},
{"learn":[0.2866917656],"iteration":195,"passed_time":3.411927335,"remaining_time":13.99586519},
{"learn":[0.2865527529],"iteration":196,"passed_time":3.427530435,"remaining_time":13.97110121},
{"learn":[0.2864468806],"iteration":197,"passed_time":3.437053495,"remaining_time":13.92180254},
{"learn":[0.2862665409],"iteration":198,"passed_time":3.44512968,"remaining_time":13.86707977},
{"learn":[0.2860578159],"iteration":199,"passed_time":3.452367285,"remaining_time":13.80946914},
{"learn":[0.2859458902],"iteration":200,"passed_time":3.459340131,"remaining_time":13.75130729},
{"learn":[0.2858568065],"iteration":201,"passed_time":3.467065205,"remaining_time":13.69662393},
{"learn":[0.2857564481],"iteration":202,"passed_time":3.476416805,"remaining_time":13.64878913},
{"learn":[0.2855539973],"iteration":203,"passed_time":3.503312316,"remaining_time":13.66978727},
{"learn":[0.2853317157],"iteration":204,"passed_time":3.543081085,"remaining_time":13.74024128},
{"learn":[0.285099696],"iteration":205,"passed_time":3.550244432,"remaining_time":13.68395184},
{"learn":[0.2849570854],"iteration":206,"passed_time":3.560340486,"remaining_time":13.63937201},
{"learn":[0.2847700702],"iteration":207,"passed_time":3.596696718,"remaining_time":13.69511442},
{"learn":[0.2847100678],"iteration":208,"passed_time":3.607216923,"remaining_time":13.65219419},
{"learn":[0.2845190114],"iteration":209,"passed_time":3.615006922,"remaining_time":13.59931175},
{"learn":[0.2843825649],"iteration":210,"passed_time":3.624425016,"remaining_time":13.55294473},
{"learn":[0.2842718383],"iteration":211,"passed_time":3.632941707,"remaining_time":13.50357578},
{"learn":[0.2840206098],"iteration":212,"passed_time":3.643447408,"remaining_time":13.46193948},
{"learn":[0.2838709317],"iteration":213,"passed_time":3.651969552,"remaining_time":13.41330873},
{"learn":[0.2836843999],"iteration":214,"passed_time":3.702493033,"remaining_time":13.5184048},
{"learn":[0.283527208],"iteration":215,"passed_time":3.731762478,"remaining_time":13.54491566},
{"learn":[0.2833924577],"iteration":216,"passed_time":3.77454503,"remaining_time":13.6196717},
{"learn":[0.283204828],"iteration":217,"passed_time":3.848607979,"remaining_time":13.80555706},
{"learn":[0.2830596392],"iteration":218,"passed_time":3.864575377,"remaining_time":13.78188753},
{"learn":[0.2829080235],"iteration":219,"passed_time":3.918776197,"remaining_time":13.89384288},
{"learn":[0.2826413048],"iteration":220,"passed_time":3.988579806,"remaining_time":14.05929262},
{"learn":[0.2824081949],"iteration":221,"passed_time":4.010012841,"remaining_time":14.05310806},
{"learn":[0.2823433125],"iteration":222,"passed_time":4.088289655,"remaining_time":14.24484781},
{"learn":[0.2822556063],"iteration":223,"passed_time":4.157977647,"remaining_time":14.40442256},
{"learn":[0.2821279486],"iteration":224,"passed_time":4.184121126,"remaining_time":14.41197277},
{"learn":[0.2820538391],"iteration":225,"passed_time":4.233589118,"remaining_time":14.49910609},
{"learn":[0.2819124192],"iteration":226,"passed_time":4.310987322,"remaining_time":14.68014626},
{"learn":[0.2818302267],"iteration":227,"passed_time":4.377139477,"remaining_time":14.82084069},
{"learn":[0.2816785974],"iteration":228,"passed_time":4.410806906,"remaining_time":14.85035862},
{"learn":[0.2815492555],"iteration":229,"passed_time":4.490817605,"remaining_time":15.03447633},
{"learn":[0.2814222202],"iteration":230,"passed_time":4.499932266,"remaining_time":14.98029399},
{"learn":[0.2813317695],"iteration":231,"passed_time":4.538297842,"remaining_time":15.02333079},
{"learn":[0.2811375282],"iteration":232,"passed_time":4.546692694,"remaining_time":14.96700986},
{"learn":[0.281041687],"iteration":233,"passed_time":4.594053488,"remaining_time":15.03865372},
{"learn":[0.2808288236],"iteration":234,"passed_time":4.641795078,"remaining_time":15.1105244},
{"learn":[0.2807078559],"iteration":235,"passed_time":4.680049655,"remaining_time":15.15066922},
{"learn":[0.280513821],"iteration":236,"passed_time":4.738924644,"remaining_time":15.25653799},
{"learn":[0.2803472608],"iteration":237,"passed_time":4.762014213,"remaining_time":15.24644887},
{"learn":[0.2802405236],"iteration":238,"passed_time":4.771103609,"remaining_time":15.191673},
{"learn":[0.280111003],"iteration":239,"passed_time":4.782154027,"remaining_time":15.14348775},
{"learn":[0.2800362276],"iteration":240,"passed_time":4.855264321,"remaining_time":15.29106066},
{"learn":[0.2799156849],"iteration":241,"passed_time":4.884660791,"remaining_time":15.29988793},
{"learn":[0.2797120847],"iteration":242,"passed_time":4.907793705,"remaining_time":15.28888821},
{"learn":[0.2795789349],"iteration":243,"passed_time":4.942403028,"remaining_time":15.31334709},
{"learn":[0.2794819394],"iteration":244,"passed_time":4.999358587,"remaining_time":15.40618667},
{"learn":[0.279318082],"iteration":245,"passed_time":5.028297119,"remaining_time":15.41193507},
{"learn":[0.2792204846],"iteration":246,"passed_time":5.048437231,"remaining_time":15.3905799},
{"learn":[0.2791030945],"iteration":247,"passed_time":5.056385434,"remaining_time":15.33226551},
{"learn":[0.2789234071],"iteration":248,"passed_time":5.067342784,"remaining_time":15.28343145},
{"learn":[0.278705372],"iteration":249,"passed_time":5.097310043,"remaining_time":15.29193013},
{"learn":[0.2785888487],"iteration":250,"passed_time":5.137417317,"remaining_time":15.33038076},
{"learn":[0.2784765131],"iteration":251,"passed_time":5.146855413,"remaining_time":15.277174},
{"learn":[0.278367815],"iteration":252,"passed_time":5.162290845,"remaining_time":15.2420208},
{"learn":[0.2782486307],"iteration":253,"passed_time":5.21490046,"remaining_time":15.31620371},
{"learn":[0.2780798465],"iteration":254,"passed_time":5.250977491,"remaining_time":15.3410911},
{"learn":[0.2778662884],"iteration":255,"passed_time":5.292490058,"remaining_time":15.38129923},
{"learn":[0.277707962],"iteration":256,"passed_time":5.364829204,"remaining_time":15.5099926},
{"learn":[0.2775866698],"iteration":257,"passed_time":5.381262788,"remaining_time":15.47634492},
{"learn":[0.2774086321],"iteration":258,"passed_time":5.400144254,"remaining_time":15.44983356},
{"learn":[0.2772073636],"iteration":259,"passed_time":5.409361683,"remaining_time":15.39587556},
{"learn":[0.2771245032],"iteration":260,"passed_time":5.432641891,"remaining_time":15.382078},
{"learn":[0.2770359646],"iteration":261,"passed_time":5.440336025,"remaining_time":15.32430529},
{"learn":[0.2768872802],"iteration":262,"passed_time":5.448198753,"remaining_time":15.26738586},
{"learn":[0.2768204938],"iteration":263,"passed_time":5.458643549,"remaining_time":15.21803656},
{"learn":[0.2766502499],"iteration":264,"passed_time":5.466388868,"remaining_time":15.16149365},
{"learn":[0.2765115144],"iteration":265,"passed_time":5.473635185,"remaining_time":15.1039407},
{"learn":[0.2763869353],"iteration":266,"passed_time":5.482621873,"remaining_time":15.05154245},
{"learn":[0.2762611459],"iteration":267,"passed_time":5.490087334,"remaining_time":14.99531317},
{"learn":[0.276257481],"iteration":268,"passed_time":5.493703006,"remaining_time":14.92898475},
{"learn":[0.2761697661],"iteration":269,"passed_time":5.500881859,"remaining_time":14.87275466},
{"learn":[0.276074329],"iteration":270,"passed_time":5.509754998,"remaining_time":14.82144426},
{"learn":[0.2759169299],"iteration":271,"passed_time":5.517274035,"remaining_time":14.76682168},
{"learn":[0.2757989655],"iteration":272,"passed_time":5.526012647,"remaining_time":14.71579192},
{"learn":[0.2757349279],"iteration":273,"passed_time":5.533768107,"remaining_time":14.66246586},
{"learn":[0.275685394],"iteration":274,"passed_time":5.543039799,"remaining_time":14.61346856},
{"learn":[0.2755423031],"iteration":275,"passed_time":5.551264372,"remaining_time":14.56201234},
{"learn":[0.2754272115],"iteration":276,"passed_time":5.559607334,"remaining_time":14.51117726},
{"learn":[0.2752935273],"iteration":277,"passed_time":5.568763645,"remaining_time":14.46276026},
{"learn":[0.2751807018],"iteration":278,"passed_time":5.576655093,"remaining_time":14.41135599},
{"learn":[0.2750557686],"iteration":279,"passed_time":5.584622803,"remaining_time":14.36045864},
{"learn":[0.275012591],"iteration":280,"passed_time":5.592403133,"remaining_time":14.30938738},
{"learn":[0.2749502721],"iteration":281,"passed_time":5.601003011,"remaining_time":14.26070979},
{"learn":[0.2747227076],"iteration":282,"passed_time":5.609610436,"remaining_time":14.21233457},
{"learn":[0.2746295627],"iteration":283,"passed_time":5.617444659,"remaining_time":14.16229006},
{"learn":[0.2745160043],"iteration":284,"passed_time":5.627175596,"remaining_time":14.11730018},
{"learn":[0.2744529608],"iteration":285,"passed_time":5.641218887,"remaining_time":14.08332267},
{"learn":[0.2742801023],"iteration":286,"passed_time":5.649064553,"remaining_time":14.0340872},
{"learn":[0.2741669453],"iteration":287,"passed_time":5.6574077,"remaining_time":13.98636904},
{"learn":[0.27405006],"iteration":288,"passed_time":5.665416571,"remaining_time":13.93810098},
{"learn":[0.2739611182],"iteration":289,"passed_time":5.673749266,"remaining_time":13.89090337},
{"learn":[0.2738032768],"iteration":290,"passed_time":5.681139833,"remaining_time":13.84167746},
{"learn":[0.2736003201],"iteration":291,"passed_time":5.689970574,"remaining_time":13.79623002},
{"learn":[0.2734995628],"iteration":292,"passed_time":5.698117434,"remaining_time":13.74938234},
{"learn":[0.2733997625],"iteration":293,"passed_time":5.707235223,"remaining_time":13.70512948},
{"learn":[0.273345539],"iteration":294,"passed_time":5.714426122,"remaining_time":13.65650988},
{"learn":[0.2732537048],"iteration":295,"passed_time":5.723108738,"remaining_time":13.61171808},
{"learn":[0.2730912021],"iteration":296,"passed_time":5.731095792,"remaining_time":13.56552304},
{"learn":[0.2729961644],"iteration":297,"passed_time":5.739623946,"remaining_time":13.52085909},
{"learn":[0.2728461598],"iteration":298,"passed_time":5.747747544,"remaining_time":13.47548839},
{"learn":[0.2727466177],"iteration":299,"passed_time":5.756546724,"remaining_time":13.43194235},
{"learn":[0.2726705985],"iteration":300,"passed_time":5.764648894,"remaining_time":13.38700856},
{"learn":[0.2725683021],"iteration":301,"passed_time":5.773296601,"remaining_time":13.34357956},
{"learn":[0.272397537],"iteration":302,"passed_time":5.781575005,"remaining_time":13.29953062},
{"learn":[0.2722905713],"iteration":303,"passed_time":5.789388386,"remaining_time":13.25465236},
{"learn":[0.2722325168],"iteration":304,"passed_time":5.796814596,"remaining_time":13.2091349},
{"learn":[0.2721060294],"iteration":305,"passed_time":5.804752136,"remaining_time":13.16502609},
{"learn":[0.2720128086],"iteration":306,"passed_time":5.813047395,"remaining_time":13.12196041},
{"learn":[0.2718383776],"iteration":307,"passed_time":5.821674844,"remaining_time":13.07986686},
{"learn":[0.2717265562],"iteration":308,"passed_time":5.829373379,"remaining_time":13.03591264},
{"learn":[0.2716186573],"iteration":309,"passed_time":5.837429542,"remaining_time":12.99298833},
{"learn":[0.271437991],"iteration":310,"passed_time":5.845618425,"remaining_time":12.9505823},
{"learn":[0.2714301849],"iteration":311,"passed_time":5.851253331,"remaining_time":12.90276375},
{"learn":[0.2713000064],"iteration":312,"passed_time":5.859530474,"remaining_time":12.86101417},
{"learn":[0.2712260594],"iteration":313,"passed_time":5.867917875,"remaining_time":12.81971867},
{"learn":[0.2710855795],"iteration":314,"passed_time":5.892791268,"remaining_time":12.8144826},
{"learn":[0.270967215],"iteration":315,"passed_time":5.930978394,"remaining_time":12.83794057},
{"learn":[0.2708312305],"iteration":316,"passed_time":5.967288798,"remaining_time":12.85696609},
{"learn":[0.2707338821],"iteration":317,"passed_time":5.988917012,"remaining_time":12.84415535},
{"learn":[0.270632669],"iteration":318,"passed_time":6.008310115,"remaining_time":12.82651783},
{"learn":[0.270552341],"iteration":319,"passed_time":6.035567487,"remaining_time":12.82558091},
{"learn":[0.2704068724],"iteration":320,"passed_time":6.055153343,"remaining_time":12.80825271},
{"learn":[0.2702165859],"iteration":321,"passed_time":6.072856225,"remaining_time":12.78694572},
{"learn":[0.2700859864],"iteration":322,"passed_time":6.091919527,"remaining_time":12.76851245},
{"learn":[0.2700021749],"iteration":323,"passed_time":6.113987635,"remaining_time":12.75634457},
{"learn":[0.269908426],"iteration":324,"passed_time":6.133225284,"remaining_time":12.73823713},
{"learn":[0.269814682],"iteration":325,"passed_time":6.162792429,"remaining_time":12.74147882},
{"learn":[0.2697524179],"iteration":326,"passed_time":6.177827146,"remaining_time":12.71461061},
{"learn":[0.2696265448],"iteration":327,"passed_time":6.207099692,"remaining_time":12.71698473},
{"learn":[0.2695147701],"iteration":328,"passed_time":6.22208962,"remaining_time":12.69003688},
{"learn":[0.2694205743],"iteration":329,"passed_time":6.24658565,"remaining_time":12.68246177},
{"learn":[0.2692636619],"iteration":330,"passed_time":6.261824728,"remaining_time":12.65607475},
{"learn":[0.2691148802],"iteration":331,"passed_time":6.272446931,"remaining_time":12.62046551},
{"learn":[0.2689659763],"iteration":332,"passed_time":6.282085765,"remaining_time":12.58303665},
{"learn":[0.2688221148],"iteration":333,"passed_time":6.300588521,"remaining_time":12.56344897},
{"learn":[0.2687076529],"iteration":334,"passed_time":6.316141721,"remaining_time":12.53801267},
{"learn":[0.2684732999],"iteration":335,"passed_time":6.339256442,"remaining_time":12.52757821},
{"learn":[0.2683928917],"iteration":336,"passed_time":6.362044881,"remaining_time":12.51642658},
{"learn":[0.2683039737],"iteration":337,"passed_time":6.386522912,"remaining_time":12.50851529},
{"learn":[0.268187385],"iteration":338,"passed_time":6.402850718,"remaining_time":12.48461453},
{"learn":[0.2679905284],"iteration":339,"passed_time":6.410548568,"remaining_time":12.44400604},
{"learn":[0.2678868174],"iteration":340,"passed_time":6.4179789,"remaining_time":12.40307359},
{"learn":[0.2677486205],"iteration":341,"passed_time":6.442447824,"remaining_time":12.39511891},
{"learn":[0.2676252078],"iteration":342,"passed_time":6.453567007,"remaining_time":12.36149715},
{"learn":[0.2674513384],"iteration":343,"passed_time":6.466455923,"remaining_time":12.33138106},
{"learn":[0.2673725792],"iteration":344,"passed_time":6.478531452,"remaining_time":12.29982058},
{"learn":[0.2673158708],"iteration":345,"passed_time":6.505411908,"remaining_time":12.29635661},
{"learn":[0.2672130846],"iteration":346,"passed_time":6.51994428,"remaining_time":12.2695205},
{"learn":[0.267055113],"iteration":347,"passed_time":6.534977994,"remaining_time":12.2436944},
{"learn":[0.2668965041],"iteration":348,"passed_time":6.549968668,"remaining_time":12.21784986},
{"learn":[0.2668313015],"iteration":349,"passed_time":6.568406033,"remaining_time":12.19846835},
{"learn":[0.2667511495],"iteration":350,"passed_time":6.587425744,"remaining_time":12.18016897},
{"learn":[0.2666223361],"iteration":351,"passed_time":6.612060891,"remaining_time":12.172203},
{"learn":[0.2664760363],"iteration":352,"passed_time":6.626780765,"remaining_time":12.14596928},
{"learn":[0.2663756361],"iteration":353,"passed_time":6.653963146,"remaining_time":12.14254292},
{"learn":[0.2663144491],"iteration":354,"passed_time":6.670666819,"remaining_time":12.11994394},
{"learn":[0.2661668868],"iteration":355,"passed_time":6.690708955,"remaining_time":12.10341732},
{"learn":[0.2660548003],"iteration":356,"passed_time":6.72105727,"remaining_time":12.10543368},
{"learn":[0.2658302796],"iteration":357,"passed_time":6.730342142,"remaining_time":12.06949624},
{"learn":[0.2655540661],"iteration":358,"passed_time":6.74638419,"remaining_time":12.04577233},
{"learn":[0.2654604178],"iteration":359,"passed_time":6.768618871,"remaining_time":12.03310022},
{"learn":[0.2653932765],"iteration":360,"passed_time":6.781975986,"remaining_time":12.00466109},
{"learn":[0.2651760785],"iteration":361,"passed_time":6.804223013,"remaining_time":11.99197316},
{"learn":[0.2650519884],"iteration":362,"passed_time":6.828219137,"remaining_time":11.9823019},
{"learn":[0.2649153369],"iteration":363,"passed_time":6.850226481,"remaining_time":11.96907704},
{"learn":[0.2647315145],"iteration":364,"passed_time":6.876466665,"remaining_time":11.96316803},
{"learn":[0.2646822223],"iteration":365,"passed_time":6.887695301,"remaining_time":11.93114432},
{"learn":[0.26453646],"iteration":366,"passed_time":6.897378239,"remaining_time":11.89656792},
{"learn":[0.2644053204],"iteration":367,"passed_time":6.911567047,"remaining_time":11.86986515},
{"learn":[0.2643351312],"iteration":368,"passed_time":6.927788903,"remaining_time":11.84670677},
{"learn":[0.2642135242],"iteration":369,"passed_time":6.984563849,"remaining_time":11.89263574},
{"learn":[0.2640291459],"iteration":370,"passed_time":6.992865727,"remaining_time":11.85582896},
{"learn":[0.2639349594],"iteration":371,"passed_time":7.011026583,"remaining_time":11.83581907},
{"learn":[0.26377012],"iteration":372,"passed_time":7.039117014,"remaining_time":11.83251037},
{"learn":[0.2636473107],"iteration":373,"passed_time":7.052324913,"remaining_time":11.80415881},
{"learn":[0.2635760065],"iteration":374,"passed_time":7.063335708,"remaining_time":11.77222618},
{"learn":[0.2634420533],"iteration":375,"passed_time":7.072849206,"remaining_time":11.73791996},
{"learn":[0.2633206496],"iteration":376,"passed_time":7.083338026,"remaining_time":11.705357},
{"learn":[0.2632018491],"iteration":377,"passed_time":7.108270156,"remaining_time":11.69667735},
{"learn":[0.2630640172],"iteration":378,"passed_time":7.138848092,"remaining_time":11.6971627},
{"learn":[0.2629288886],"iteration":379,"passed_time":7.162328817,"remaining_time":11.68590491},
{"learn":[0.262709689],"iteration":380,"passed_time":7.189861318,"remaining_time":11.68116576},
{"learn":[0.2625677699],"iteration":381,"passed_time":7.208039379,"remaining_time":11.66117366},
{"learn":[0.262446809],"iteration":382,"passed_time":7.225057147,"remaining_time":11.63932183},
{"learn":[0.2622962704],"iteration":383,"passed_time":7.249884542,"remaining_time":11.63002312},
{"learn":[0.2621360226],"iteration":384,"passed_time":7.267416329,"remaining_time":11.60898972},
{"learn":[0.2620162684],"iteration":385,"passed_time":7.278642288,"remaining_time":11.57794395},
{"learn":[0.2619046997],"iteration":386,"passed_time":7.294701127,"remaining_time":11.55465579},
{"learn":[0.2618067713],"iteration":387,"passed_time":7.307588889,"remaining_time":11.52640309},
{"learn":[0.2616871801],"iteration":388,"passed_time":7.337381128,"remaining_time":11.52478115},
{"learn":[0.2615614337],"iteration":389,"passed_time":7.364616879,"remaining_time":11.51901614},
{"learn":[0.2614394428],"iteration":390,"passed_time":7.419042473,"remaining_time":11.55549071},
{"learn":[0.2613310294],"iteration":391,"passed_time":7.42766796,"remaining_time":11.52046459},
{"learn":[0.2612512123],"iteration":392,"passed_time":7.436767138,"remaining_time":11.48630446},
{"learn":[0.2611453369],"iteration":393,"passed_time":7.459703267,"remaining_time":11.47355376},
{"learn":[0.2609453582],"iteration":394,"passed_time":7.482116464,"remaining_time":11.45995053},
{"learn":[0.2607488842],"iteration":395,"passed_time":7.513141446,"remaining_time":11.45943796},
{"learn":[0.2605803351],"iteration":396,"passed_time":7.529550292,"remaining_time":11.43657135},
{"learn":[0.2604473752],"iteration":397,"passed_time":7.558579864,"remaining_time":11.43282683},
{"learn":[0.260213961],"iteration":398,"passed_time":7.578124705,"remaining_time":11.41466904},
{"learn":[0.2600723515],"iteration":399,"passed_time":7.592454595,"remaining_time":11.38868189},
{"learn":[0.2599351839],"iteration":400,"passed_time":7.611485114,"remaining_time":11.36977452},
{"learn":[0.2598170229],"iteration":401,"passed_time":7.648418907,"remaining_time":11.37749877},
{"learn":[0.2597025999],"iteration":402,"passed_time":7.663885529,"remaining_time":11.35320015},
{"learn":[0.2596139079],"iteration":403,"passed_time":7.676778365,"remaining_time":11.32514828},
{"learn":[0.2595593843],"iteration":404,"passed_time":7.692396332,"remaining_time":11.30117486},
{"learn":[0.2593967704],"iteration":405,"passed_time":7.710570184,"remaining_time":11.28098199},
{"learn":[0.2593487148],"iteration":406,"passed_time":7.731445084,"remaining_time":11.26473448},
{"learn":[0.2591225349],"iteration":407,"passed_time":7.761592765,"remaining_time":11.26191891},
{"learn":[0.2590096558],"iteration":408,"passed_time":7.778993738,"remaining_time":11.24055085},
{"learn":[0.2588754758],"iteration":409,"passed_time":7.79706419,"remaining_time":11.22016554},
{"learn":[0.2586265775],"iteration":410,"passed_time":7.808306958,"remaining_time":11.19000681},
{"learn":[0.2585052062],"iteration":411,"passed_time":7.820301835,"remaining_time":11.1610133},
{"learn":[0.2584293561],"iteration":412,"passed_time":7.83260502,"remaining_time":11.13254031},
{"learn":[0.2582998934],"iteration":413,"passed_time":7.848260098,"remaining_time":11.1088899},
{"learn":[0.2581789045],"iteration":414,"passed_time":7.859358451,"remaining_time":11.07885468},
{"learn":[0.2580733092],"iteration":415,"passed_time":7.882643101,"remaining_time":11.0660182},
{"learn":[0.2579895556],"iteration":416,"passed_time":7.895912229,"remaining_time":11.03912909},
{"learn":[0.2579256281],"iteration":417,"passed_time":7.903075581,"remaining_time":11.0038038},
{"learn":[0.2578672249],"iteration":418,"passed_time":7.911264114,"remaining_time":10.97003449},
{"learn":[0.2577803913],"iteration":419,"passed_time":7.917986302,"remaining_time":10.93436204},
{"learn":[0.2576541579],"iteration":420,"passed_time":7.956630019,"remaining_time":10.9427287},
{"learn":[0.2576110777],"iteration":421,"passed_time":7.989040901,"remaining_time":10.94233564},
{"learn":[0.2574521791],"iteration":422,"passed_time":8.013305081,"remaining_time":10.93067856},
{"learn":[0.2573774421],"iteration":423,"passed_time":8.025537548,"remaining_time":10.90261705},
{"learn":[0.2572825672],"iteration":424,"passed_time":8.034233534,"remaining_time":10.86984537},
{"learn":[0.2571901593],"iteration":425,"passed_time":8.053824872,"remaining_time":10.85186732},
{"learn":[0.2570550762],"iteration":426,"passed_time":8.072818187,"remaining_time":10.83307921},
{"learn":[0.2569727536],"iteration":427,"passed_time":8.088818737,"remaining_time":10.81029046},
{"learn":[0.2568437085],"iteration":428,"passed_time":8.104760426,"remaining_time":10.78745502},
{"learn":[0.2566684688],"iteration":429,"passed_time":8.123738279,"remaining_time":10.76867632},
{"learn":[0.2565320246],"iteration":430,"passed_time":8.154651358,"remaining_time":10.76565342},
{"learn":[0.2563793909],"iteration":431,"passed_time":8.169110891,"remaining_time":10.74086802},
{"learn":[0.2562993489],"iteration":432,"passed_time":8.183149456,"remaining_time":10.71557908},
{"learn":[0.2561155446],"iteration":433,"passed_time":8.199528003,"remaining_time":10.69339366},
{"learn":[0.2560255556],"iteration":434,"passed_time":8.221747564,"remaining_time":10.67882155},
{"learn":[0.2559647184],"iteration":435,"passed_time":8.313891043,"remaining_time":10.75466639},
{"learn":[0.2558446028],"iteration":436,"passed_time":8.337424633,"remaining_time":10.74135027},
{"learn":[0.2557357653],"iteration":437,"passed_time":8.358654619,"remaining_time":10.72503173},
{"learn":[0.2556308259],"iteration":438,"passed_time":8.388390915,"remaining_time":10.71956106},
{"learn":[0.2555475213],"iteration":439,"passed_time":8.406028398,"remaining_time":10.6985816},
{"learn":[0.2554434873],"iteration":440,"passed_time":8.415736082,"remaining_time":10.66756569},
{"learn":[0.255370642],"iteration":441,"passed_time":8.424359102,"remaining_time":10.63527688},
{"learn":[0.2552340928],"iteration":442,"passed_time":8.43404001,"remaining_time":10.60442502},
{"learn":[0.2550834251],"iteration":443,"passed_time":8.472754003,"remaining_time":10.61002528},
{"learn":[0.25492971],"iteration":444,"passed_time":8.504330475,"remaining_time":10.60652453},
{"learn":[0.2547677271],"iteration":445,"passed_time":8.513839842,"remaining_time":10.57548716},
{"learn":[0.2545920703],"iteration":446,"passed_time":8.522370132,"remaining_time":10.54333486},
{"learn":[0.2545006296],"iteration":447,"passed_time":8.550430697,"remaining_time":10.53535211},
{"learn":[0.2544061589],"iteration":448,"passed_time":8.580627381,"remaining_time":10.52990131},
{"learn":[0.2542683898],"iteration":449,"passed_time":8.601837045,"remaining_time":10.51335639},
{"learn":[0.2541602067],"iteration":450,"passed_time":8.628677932,"remaining_time":10.50364564},
{"learn":[0.2540955498],"iteration":451,"passed_time":8.637310777,"remaining_time":10.47178386},
{"learn":[0.2539380335],"iteration":452,"passed_time":8.686012974,"remaining_time":10.4884086},
{"learn":[0.2538900105],"iteration":453,"passed_time":8.694697545,"remaining_time":10.45661863},
{"learn":[0.2537918601],"iteration":454,"passed_time":8.703601948,"remaining_time":10.42519354},
{"learn":[0.2536859075],"iteration":455,"passed_time":8.730995133,"remaining_time":10.41592402},
{"learn":[0.2535307533],"iteration":456,"passed_time":8.759103865,"remaining_time":10.40742538},
{"learn":[0.2534417878],"iteration":457,"passed_time":8.777990945,"remaining_time":10.38792815},
{"learn":[0.2533077085],"iteration":458,"passed_time":8.803177033,"remaining_time":10.3758579},
{"learn":[0.2531604492],"iteration":459,"passed_time":8.833655667,"remaining_time":10.36994361},
{"learn":[0.2530514227],"iteration":460,"passed_time":8.847130543,"remaining_time":10.344042},
{"learn":[0.2529888034],"iteration":461,"passed_time":8.872497154,"remaining_time":10.33204214},
{"learn":[0.2528338519],"iteration":462,"passed_time":8.89308192,"remaining_time":10.31443843},
{"learn":[0.2526919938],"iteration":463,"passed_time":8.908938507,"remaining_time":10.29136},
{"learn":[0.2524712392],"iteration":464,"passed_time":8.918457951,"remaining_time":10.26102151},
{"learn":[0.2523514095],"iteration":465,"passed_time":8.944489519,"remaining_time":10.249694},
{"learn":[0.2522353053],"iteration":466,"passed_time":8.963955109,"remaining_time":10.23080958},
{"learn":[0.2521321523],"iteration":467,"passed_time":8.976338206,"remaining_time":10.20387164},
{"learn":[0.2520272032],"iteration":468,"passed_time":8.989460784,"remaining_time":10.177833},
{"learn":[0.2519318923],"iteration":469,"passed_time":8.997453966,"remaining_time":10.14606511},
{"learn":[0.2518056694],"iteration":470,"passed_time":9.008348834,"remaining_time":10.11765718},
{"learn":[0.2515982612],"iteration":471,"passed_time":9.017472843,"remaining_time":10.0873425},
{"learn":[0.251485989],"iteration":472,"passed_time":9.043090904,"remaining_time":10.07549452},
{"learn":[0.2513976265],"iteration":473,"passed_time":9.091520344,"remaining_time":10.08890232},
{"learn":[0.2512466788],"iteration":474,"passed_time":9.100073875,"remaining_time":10.05797639},
{"learn":[0.2511163814],"iteration":475,"passed_time":9.156043581,"remaining_time":10.07934209},
{"learn":[0.2510888539],"iteration":476,"passed_time":9.171120377,"remaining_time":10.05554708},
{"learn":[0.2509507321],"iteration":477,"passed_time":9.198639095,"remaining_time":10.04537575},
{"learn":[0.2508674303],"iteration":478,"passed_time":9.207625704,"remaining_time":10.01497493},
{"learn":[0.2507893641],"iteration":479,"passed_time":9.260965234,"remaining_time":10.03271234},
{"learn":[0.2507006627],"iteration":480,"passed_time":9.295105248,"remaining_time":10.02943789},
{"learn":[0.250588061],"iteration":481,"passed_time":9.336999181,"remaining_time":10.03436841},
{"learn":[0.2504816808],"iteration":482,"passed_time":9.374990523,"remaining_time":10.03492774},
{"learn":[0.2504180965],"iteration":483,"passed_time":9.381952027,"remaining_time":10.00224638},
{"learn":[0.2503123899],"iteration":484,"passed_time":9.38884834,"remaining_time":9.969601846},
{"learn":[0.2502531116],"iteration":485,"passed_time":9.395816949,"remaining_time":9.937139736},
{"learn":[0.2501562759],"iteration":486,"passed_time":9.418069382,"remaining_time":9.920882121},
{"learn":[0.2499977211],"iteration":487,"passed_time":9.426465294,"remaining_time":9.890061948},
{"learn":[0.2499177643],"iteration":488,"passed_time":9.434232596,"remaining_time":9.858676598},
{"learn":[0.2497784538],"iteration":489,"passed_time":9.448285598,"remaining_time":9.833929909},
{"learn":[0.2496825128],"iteration":490,"passed_time":9.47045382,"remaining_time":9.8176395},
{"learn":[0.2495648322],"iteration":491,"passed_time":9.497069135,"remaining_time":9.805916912},
{"learn":[0.2494905867],"iteration":492,"passed_time":9.517884929,"remaining_time":9.788169694},
{"learn":[0.2493988732],"iteration":493,"passed_time":9.529459664,"remaining_time":9.760944514},
{"learn":[0.2492444708],"iteration":494,"passed_time":9.551220422,"remaining_time":9.74417437},
{"learn":[0.2491161018],"iteration":495,"passed_time":9.560063714,"remaining_time":9.71425829},
{"learn":[0.2489933536],"iteration":496,"passed_time":9.57290195,"remaining_time":9.688470182},
{"learn":[0.2489037842],"iteration":497,"passed_time":9.585545993,"remaining_time":9.66253833},
{"learn":[0.2488465167],"iteration":498,"passed_time":9.594073699,"remaining_time":9.6325269},
{"learn":[0.2487411966],"iteration":499,"passed_time":9.603512746,"remaining_time":9.603512746},
{"learn":[0.2486691001],"iteration":500,"passed_time":9.611910605,"remaining_time":9.573539704},
{"learn":[0.2485620886],"iteration":501,"passed_time":9.621406627,"remaining_time":9.544742032},
{"learn":[0.2485235407],"iteration":502,"passed_time":9.631313764,"remaining_time":9.516427317},
{"learn":[0.2484245782],"iteration":503,"passed_time":9.642109778,"remaining_time":9.489060416},
{"learn":[0.2483346921],"iteration":504,"passed_time":9.649684505,"remaining_time":9.458601643},
{"learn":[0.2482487493],"iteration":505,"passed_time":9.657186338,"remaining_time":9.428162156},
{"learn":[0.2481226431],"iteration":506,"passed_time":9.664117752,"remaining_time":9.397258485},
{"learn":[0.2480018675],"iteration":507,"passed_time":9.671359955,"remaining_time":9.366750193},
{"learn":[0.2479068865],"iteration":508,"passed_time":9.678780589,"remaining_time":9.33650544},
{"learn":[0.2477659958],"iteration":509,"passed_time":9.686094016,"remaining_time":9.306247192},
{"learn":[0.2476639466],"iteration":510,"passed_time":9.693036207,"remaining_time":9.275723493},
{"learn":[0.247511803],"iteration":511,"passed_time":9.700287283,"remaining_time":9.245586316},
{"learn":[0.2473813803],"iteration":512,"passed_time":9.707550504,"remaining_time":9.215549894},
{"learn":[0.2472636689],"iteration":513,"passed_time":9.715661537,"remaining_time":9.18640371},
{"learn":[0.2471391319],"iteration":514,"passed_time":9.723199098,"remaining_time":9.15679915},
{"learn":[0.2471142364],"iteration":515,"passed_time":9.730316029,"remaining_time":9.126885578},
{"learn":[0.2470565514],"iteration":516,"passed_time":9.739666797,"remaining_time":9.099147124},
{"learn":[0.2469691319],"iteration":517,"passed_time":9.746387515,"remaining_time":9.069032398},
{"learn":[0.2468799327],"iteration":518,"passed_time":9.752975599,"remaining_time":9.0388849},
{"learn":[0.2467331862],"iteration":519,"passed_time":9.760740784,"remaining_time":9.009914569},
{"learn":[0.2466862191],"iteration":520,"passed_time":9.76793199,"remaining_time":8.980497933},
{"learn":[0.2465358126],"iteration":521,"passed_time":9.774970513,"remaining_time":8.951026639},
{"learn":[0.2464142706],"iteration":522,"passed_time":9.782455094,"remaining_time":8.922047954},
{"learn":[0.2462619655],"iteration":523,"passed_time":9.789446612,"remaining_time":8.89270341},
{"learn":[0.2461440358],"iteration":524,"passed_time":9.796507797,"remaining_time":8.863507055},
{"learn":[0.2460903526],"iteration":525,"passed_time":9.803311979,"remaining_time":8.834163266},
{"learn":[0.2459965263],"iteration":526,"passed_time":9.810661104,"remaining_time":8.805394122},
{"learn":[0.2458947224],"iteration":527,"passed_time":9.818242003,"remaining_time":8.776913306},
{"learn":[0.2457904562],"iteration":528,"passed_time":9.825551331,"remaining_time":8.748269711},
{"learn":[0.2457027438],"iteration":529,"passed_time":9.833155151,"remaining_time":8.719967775},
{"learn":[0.2456608877],"iteration":530,"passed_time":9.839780984,"remaining_time":8.690880003},
{"learn":[0.2455291485],"iteration":531,"passed_time":9.846913625,"remaining_time":8.662322512},
{"learn":[0.2454557882],"iteration":532,"passed_time":9.856316094,"remaining_time":8.635834176},
{"learn":[0.245374302],"iteration":533,"passed_time":9.863804827,"remaining_time":8.607739793},
{"learn":[0.2452759105],"iteration":534,"passed_time":9.87139595,"remaining_time":8.579811433},
{"learn":[0.2452072769],"iteration":535,"passed_time":9.87879389,"remaining_time":8.551791725},
{"learn":[0.2451095459],"iteration":536,"passed_time":9.88636454,"remaining_time":8.523997732},
{"learn":[0.2450563269],"iteration":537,"passed_time":9.893765081,"remaining_time":8.496132839},
{"learn":[0.2449363936],"iteration":538,"passed_time":9.901008833,"remaining_time":8.468209781},
{"learn":[0.2448446918],"iteration":539,"passed_time":9.907818545,"remaining_time":8.439993576},
{"learn":[0.2447625184],"iteration":540,"passed_time":9.914584693,"remaining_time":8.411819545},
{"learn":[0.2447120701],"iteration":541,"passed_time":9.922467967,"remaining_time":8.384668504},
{"learn":[0.2445715877],"iteration":542,"passed_time":9.929681186,"remaining_time":8.357024497},
{"learn":[0.2444925587],"iteration":543,"passed_time":9.936838679,"remaining_time":8.329408893},
{"learn":[0.2443990899],"iteration":544,"passed_time":9.944358317,"remaining_time":8.302170705},
{"learn":[0.2443283766],"iteration":545,"passed_time":9.952944957,"remaining_time":8.275891961},
{"learn":[0.244241463],"iteration":546,"passed_time":9.960828619,"remaining_time":8.249095731},
{"learn":[0.2440403568],"iteration":547,"passed_time":9.967921104,"remaining_time":8.221715947},
{"learn":[0.2439896493],"iteration":548,"passed_time":9.976159689,"remaining_time":8.195351584},
{"learn":[0.2439122743],"iteration":549,"passed_time":9.983835093,"remaining_time":8.168592349},
{"learn":[0.2438367853],"iteration":550,"passed_time":9.991399618,"remaining_time":8.14181203},
{"learn":[0.2437683694],"iteration":551,"passed_time":9.998898167,"remaining_time":8.115047788},
{"learn":[0.2437040348],"iteration":552,"passed_time":10.00670343,"remaining_time":8.088601144},
{"learn":[0.2436345342],"iteration":553,"passed_time":10.01387074,"remaining_time":8.061708215},
{"learn":[0.2434908765],"iteration":554,"passed_time":10.02140492,"remaining_time":8.03518052},
{"learn":[0.2434575536],"iteration":555,"passed_time":10.02833957,"remaining_time":8.008242393},
{"learn":[0.2433829538],"iteration":556,"passed_time":10.03524783,"remaining_time":7.981355099},
{"learn":[0.2432738108],"iteration":557,"passed_time":10.04296729,"remaining_time":7.955181972},
{"learn":[0.2432215122],"iteration":558,"passed_time":10.05043017,"remaining_time":7.928872461},
{"learn":[0.2431258266],"iteration":559,"passed_time":10.05877895,"remaining_time":7.903326319},
{"learn":[0.24305978],"iteration":560,"passed_time":10.06645282,"remaining_time":7.87731335},
{"learn":[0.2429657996],"iteration":561,"passed_time":10.07418558,"remaining_time":7.85141154},
{"learn":[0.2429081732],"iteration":562,"passed_time":10.08394985,"remaining_time":7.827151131},
{"learn":[0.2428141207],"iteration":563,"passed_time":10.0949974,"remaining_time":7.803934163},
{"learn":[0.2427140272],"iteration":564,"passed_time":10.11039256,"remaining_time":7.784107547},
{"learn":[0.2426317511],"iteration":565,"passed_time":10.12148232,"remaining_time":7.760995274},
{"learn":[0.2424640074],"iteration":566,"passed_time":10.12984499,"remaining_time":7.735842823},
{"learn":[0.2423871048],"iteration":567,"passed_time":10.13847494,"remaining_time":7.710952775},
{"learn":[0.242288681],"iteration":568,"passed_time":10.1458396,"remaining_time":7.685161456},
{"learn":[0.2422108854],"iteration":569,"passed_time":10.15287344,"remaining_time":7.659185228},
{"learn":[0.2420904695],"iteration":570,"passed_time":10.15985373,"remaining_time":7.633235116},
{"learn":[0.2420319582],"iteration":571,"passed_time":10.16845898,"remaining_time":7.608567208},
{"learn":[0.2419224603],"iteration":572,"passed_time":10.17714645,"remaining_time":7.584016639},
{"learn":[0.2418190766],"iteration":573,"passed_time":10.18719032,"remaining_time":7.560528004},
{"learn":[0.2417691479],"iteration":574,"passed_time":10.1949405,"remaining_time":7.535390807},
{"learn":[0.2416750915],"iteration":575,"passed_time":10.20206946,"remaining_time":7.509856689},
{"learn":[0.2415519714],"iteration":576,"passed_time":10.2103377,"remaining_time":7.485221574},
{"learn":[0.241472517],"iteration":577,"passed_time":10.21778293,"remaining_time":7.46004221},
{"learn":[0.2413576457],"iteration":578,"passed_time":10.22499947,"remaining_time":7.434757817},
{"learn":[0.2412790923],"iteration":579,"passed_time":10.23196528,"remaining_time":7.40935417},
{"learn":[0.2412119132],"iteration":580,"passed_time":10.23923638,"remaining_time":7.384234151},
{"learn":[0.2411400574],"iteration":581,"passed_time":10.24651002,"remaining_time":7.3591773},
{"learn":[0.2410595787],"iteration":582,"passed_time":10.25456844,"remaining_time":7.33474278},
{"learn":[0.2409234113],"iteration":583,"passed_time":10.26579574,"remaining_time":7.312621621},
{"learn":[0.2408765417],"iteration":584,"passed_time":10.27344211,"remaining_time":7.287997397},
{"learn":[0.2408047118],"iteration":585,"passed_time":10.28271521,"remaining_time":7.264580368},
{"learn":[0.2407151906],"iteration":586,"passed_time":10.29017054,"remaining_time":7.239932591},
{"learn":[0.240641864],"iteration":587,"passed_time":10.29863811,"remaining_time":7.216052552},
{"learn":[0.2404900669],"iteration":588,"passed_time":10.30622308,"remaining_time":7.191608976},
{"learn":[0.2404272667],"iteration":589,"passed_time":10.31299326,"remaining_time":7.16665633},
{"learn":[0.2403009362],"iteration":590,"passed_time":10.32010008,"remaining_time":7.141998197},
{"learn":[0.2401967943],"iteration":591,"passed_time":10.3299828,"remaining_time":7.11931247},
{"learn":[0.2401283767],"iteration":592,"passed_time":10.33764711,"remaining_time":7.09514734},
{"learn":[0.2400484269],"iteration":593,"passed_time":10.36539745,"remaining_time":7.084766608},
{"learn":[0.2399164158],"iteration":594,"passed_time":10.38688113,"remaining_time":7.070061949},
{"learn":[0.2398558009],"iteration":595,"passed_time":10.39625686,"remaining_time":7.047127132},
{"learn":[0.2398235266],"iteration":596,"passed_time":10.40505556,"remaining_time":7.023848226},
{"learn":[0.239744009],"iteration":597,"passed_time":10.41814717,"remaining_time":7.003503615},
{"learn":[0.2396376769],"iteration":598,"passed_time":10.44919866,"remaining_time":6.995206447},
{"learn":[0.2394855517],"iteration":599,"passed_time":10.46232329,"remaining_time":6.974882192},
{"learn":[0.2393986263],"iteration":600,"passed_time":10.47246089,"remaining_time":6.952598829},
{"learn":[0.2393421185],"iteration":601,"passed_time":10.48803109,"remaining_time":6.933947462},
{"learn":[0.2392246464],"iteration":602,"passed_time":10.50495048,"remaining_time":6.916194594},
{"learn":[0.2391773793],"iteration":603,"passed_time":10.52134605,"remaining_time":6.898101052},
{"learn":[0.2390503983],"iteration":604,"passed_time":10.54687757,"remaining_time":6.885977915},
{"learn":[0.2390021547],"iteration":605,"passed_time":10.57628026,"remaining_time":6.876327429},
{"learn":[0.2388923982],"iteration":606,"passed_time":10.59709993,"remaining_time":6.861054812},
{"learn":[0.2388019959],"iteration":607,"passed_time":10.6257107,"remaining_time":6.850787163},
{"learn":[0.2386429866],"iteration":608,"passed_time":10.65919754,"remaining_time":6.84358988},
{"learn":[0.2385603246],"iteration":609,"passed_time":10.68568831,"remaining_time":6.831833511},
{"learn":[0.2384713677],"iteration":610,"passed_time":10.70807704,"remaining_time":6.8174173},
{"learn":[0.2384065489],"iteration":611,"passed_time":10.73303486,"remaining_time":6.804603798},
{"learn":[0.2382808183],"iteration":612,"passed_time":10.74255495,"remaining_time":6.782004514},
{"learn":[0.2382363536],"iteration":613,"passed_time":10.750866,"remaining_time":6.758687743},
{"learn":[0.2380938154],"iteration":614,"passed_time":10.75982934,"remaining_time":6.735828125},
{"learn":[0.2380432033],"iteration":615,"passed_time":10.76806173,"remaining_time":6.712557964},
{"learn":[0.2379915718],"iteration":616,"passed_time":10.77631526,"remaining_time":6.689349668},
{"learn":[0.237880467],"iteration":617,"passed_time":10.78481793,"remaining_time":6.666343771},
{"learn":[0.2377899373],"iteration":618,"passed_time":10.79350808,"remaining_time":6.643500128},
{"learn":[0.2376889987],"iteration":619,"passed_time":10.80291703,"remaining_time":6.621142697},
{"learn":[0.2375943464],"iteration":620,"passed_time":10.81159068,"remaining_time":6.59837821},
{"learn":[0.2374836277],"iteration":621,"passed_time":10.82113846,"remaining_time":6.576190251},
{"learn":[0.2373547997],"iteration":622,"passed_time":10.86745125,"remaining_time":6.576290725},
{"learn":[0.2372736077],"iteration":623,"passed_time":10.879752,"remaining_time":6.555747999},
{"learn":[0.2372288665],"iteration":624,"passed_time":10.89439123,"remaining_time":6.536634737},
{"learn":[0.2371475363],"iteration":625,"passed_time":10.9027255,"remaining_time":6.513768906},
{"learn":[0.2370583339],"iteration":626,"passed_time":10.94096154,"remaining_time":6.508737885},
{"learn":[0.2369616784],"iteration":627,"passed_time":10.99173775,"remaining_time":6.51102937},
{"learn":[0.2368688791],"iteration":628,"passed_time":11.00485632,"remaining_time":6.490940693},
{"learn":[0.2368158365],"iteration":629,"passed_time":11.02695864,"remaining_time":6.476150315},
{"learn":[0.2367433442],"iteration":630,"passed_time":11.04056318,"remaining_time":6.456367374},
{"learn":[0.2366571358],"iteration":631,"passed_time":11.05257607,"remaining_time":6.435677204},
{"learn":[0.236577216],"iteration":632,"passed_time":11.06026556,"remaining_time":6.412507834},
{"learn":[0.2365102637],"iteration":633,"passed_time":11.06876929,"remaining_time":6.389857349},
{"learn":[0.2364396777],"iteration":634,"passed_time":11.0761758,"remaining_time":6.366620737},
{"learn":[0.2363360199],"iteration":635,"passed_time":11.08627594,"remaining_time":6.344975538},
{"learn":[0.2362475388],"iteration":636,"passed_time":11.09376758,"remaining_time":6.321880111},
{"learn":[0.2361623275],"iteration":637,"passed_time":11.1033373,"remaining_time":6.300012699},
{"learn":[0.2360654566],"iteration":638,"passed_time":11.11034488,"remaining_time":6.276736311},
{"learn":[0.2359478692],"iteration":639,"passed_time":11.11874046,"remaining_time":6.254291507},
{"learn":[0.235905904],"iteration":640,"passed_time":11.12576797,"remaining_time":6.231124341},
{"learn":[0.2358521791],"iteration":641,"passed_time":11.1339915,"remaining_time":6.208674385},
{"learn":[0.2358176853],"iteration":642,"passed_time":11.14014007,"remaining_time":6.185116646},
{"learn":[0.2357370749],"iteration":643,"passed_time":11.14862243,"remaining_time":6.162903081},
{"learn":[0.2356434057],"iteration":644,"passed_time":11.15696225,"remaining_time":6.14065364},
{"learn":[0.2355759473],"iteration":645,"passed_time":11.16497682,"remaining_time":6.11826903},
{"learn":[0.2355266841],"iteration":646,"passed_time":11.17164177,"remaining_time":6.095192494},
{"learn":[0.235462544],"iteration":647,"passed_time":11.17963768,"remaining_time":6.072889602},
{"learn":[0.2353730854],"iteration":648,"passed_time":11.18612557,"remaining_time":6.049815214},
{"learn":[0.2353181066],"iteration":649,"passed_time":11.19390939,"remaining_time":6.027489671},
{"learn":[0.235235159],"iteration":650,"passed_time":11.20035159,"remaining_time":6.004489564},
{"learn":[0.235128462],"iteration":651,"passed_time":11.20742657,"remaining_time":5.981877985},
{"learn":[0.2349895613],"iteration":652,"passed_time":11.21671441,"remaining_time":5.960489893},
{"learn":[0.2348969375],"iteration":653,"passed_time":11.22597211,"remaining_time":5.939122862},
{"learn":[0.2347923928],"iteration":654,"passed_time":11.2353512,"remaining_time":5.917856737},
{"learn":[0.2347175318],"iteration":655,"passed_time":11.24386549,"remaining_time":5.896173367},
{"learn":[0.2346180519],"iteration":656,"passed_time":11.25136956,"remaining_time":5.874002675},
{"learn":[0.2345529481],"iteration":657,"passed_time":11.25992326,"remaining_time":5.852422119},
{"learn":[0.2344758225],"iteration":658,"passed_time":11.26704924,"remaining_time":5.830142323},
{"learn":[0.2344011709],"iteration":659,"passed_time":11.27445849,"remaining_time":5.808054375},
{"learn":[0.2343064477],"iteration":660,"passed_time":11.28128004,"remaining_time":5.785709432},
{"learn":[0.234209372],"iteration":661,"passed_time":11.29013566,"remaining_time":5.764449928},
{"learn":[0.2340763179],"iteration":662,"passed_time":11.29765302,"remaining_time":5.742547615},
{"learn":[0.2339730703],"iteration":663,"passed_time":11.30658367,"remaining_time":5.721403785},
{"learn":[0.2338720176],"iteration":664,"passed_time":11.31463092,"remaining_time":5.699851667},
{"learn":[0.2338279969],"iteration":665,"passed_time":11.32549691,"remaining_time":5.679753705},
{"learn":[0.2337397637],"iteration":666,"passed_time":11.33300053,"remaining_time":5.658004764},
{"learn":[0.2336494572],"iteration":667,"passed_time":11.33977795,"remaining_time":5.635937542},
{"learn":[0.2335964865],"iteration":668,"passed_time":11.34698617,"remaining_time":5.614129181},
{"learn":[0.2335259618],"iteration":669,"passed_time":11.35485028,"remaining_time":5.592687451},
{"learn":[0.2334346031],"iteration":670,"passed_time":11.3633969,"remaining_time":5.571620837},
{"learn":[0.2333460821],"iteration":671,"passed_time":11.37078242,"remaining_time":5.550024752},
{"learn":[0.2332768377],"iteration":672,"passed_time":11.37891035,"remaining_time":5.528831628},
{"learn":[0.233196903],"iteration":673,"passed_time":11.38699832,"remaining_time":5.507657939},
{"learn":[0.2331449732],"iteration":674,"passed_time":11.39464485,"remaining_time":5.486310485},
{"learn":[0.2330768394],"iteration":675,"passed_time":11.40345016,"remaining_time":5.465558952},
{"learn":[0.2329779708],"iteration":676,"passed_time":11.411815,"remaining_time":5.444632564},
{"learn":[0.232931552],"iteration":677,"passed_time":11.41928426,"remaining_time":5.423317893},
{"learn":[0.232811324],"iteration":678,"passed_time":11.42917709,"remaining_time":5.403189756},
{"learn":[0.2327170152],"iteration":679,"passed_time":11.45925836,"remaining_time":5.392592168},
{"learn":[0.2325504495],"iteration":680,"passed_time":11.46772088,"remaining_time":5.371810517},
{"learn":[0.2325003536],"iteration":681,"passed_time":11.47820274,"remaining_time":5.352006554},
{"learn":[0.2324058241],"iteration":682,"passed_time":11.51734178,"remaining_time":5.345530521},
{"learn":[0.2323587337],"iteration":683,"passed_time":11.52824133,"remaining_time":5.325912662},
{"learn":[0.2322843086],"iteration":684,"passed_time":11.55899197,"remaining_time":5.31544886},
{"learn":[0.2321862044],"iteration":685,"passed_time":11.58242195,"remaining_time":5.301575062},
{"learn":[0.2320808002],"iteration":686,"passed_time":11.6046357,"remaining_time":5.287119322},
{"learn":[0.2318993248],"iteration":687,"passed_time":11.61686155,"remaining_time":5.268111634},
{"learn":[0.231762957],"iteration":688,"passed_time":11.63329298,"remaining_time":5.251021939},
{"learn":[0.2317061028],"iteration":689,"passed_time":11.64370137,"remaining_time":5.23122815},
{"learn":[0.2315893353],"iteration":690,"passed_time":11.68871695,"remaining_time":5.226937101},
{"learn":[0.2314836899],"iteration":691,"passed_time":11.6967721,"remaining_time":5.206077756},
{"learn":[0.2313953141],"iteration":692,"passed_time":11.70785808,"remaining_time":5.186598026},
{"learn":[0.2313167324],"iteration":693,"passed_time":11.71921161,"remaining_time":5.167260451},
{"learn":[0.2312284464],"iteration":694,"passed_time":11.72985598,"remaining_time":5.147634638},
{"learn":[0.2311794019],"iteration":695,"passed_time":11.73924323,"remaining_time":5.127485548},
{"learn":[0.231117612],"iteration":696,"passed_time":11.75093974,"remaining_time":5.108371221},
{"learn":[0.2310795515],"iteration":697,"passed_time":11.7599017,"remaining_time":5.088095007},
{"learn":[0.2309879557],"iteration":698,"passed_time":11.78483653,"remaining_time":5.074729321},
{"learn":[0.2308849874],"iteration":699,"passed_time":11.80719531,"remaining_time":5.060226562},
{"learn":[0.2308064773],"iteration":700,"passed_time":11.8360479,"remaining_time":5.048471216},
{"learn":[0.2307614284],"iteration":701,"passed_time":11.8573077,"remaining_time":5.033444008},
{"learn":[0.2306953491],"iteration":702,"passed_time":11.86778625,"remaining_time":5.013844261},
{"learn":[0.2306075956],"iteration":703,"passed_time":11.87929438,"remaining_time":4.994703318},
{"learn":[0.2304859749],"iteration":704,"passed_time":11.89495883,"remaining_time":4.977323197},
{"learn":[0.2304045408],"iteration":705,"passed_time":11.90360151,"remaining_time":4.957023859},
{"learn":[0.230362422],"iteration":706,"passed_time":11.91406184,"remaining_time":4.937510775},
{"learn":[0.230234808],"iteration":707,"passed_time":11.92261398,"remaining_time":4.917236273},
{"learn":[0.2301878782],"iteration":708,"passed_time":11.93001608,"remaining_time":4.896522819},
{"learn":[0.2301058649],"iteration":709,"passed_time":11.93741077,"remaining_time":4.875843837},
{"learn":[0.2299836073],"iteration":710,"passed_time":11.94568889,"remaining_time":4.855561307},
{"learn":[0.2297993856],"iteration":711,"passed_time":11.95292625,"remaining_time":4.834891517},
{"learn":[0.2297236106],"iteration":712,"passed_time":11.9623634,"remaining_time":4.815144876},
{"learn":[0.2296181223],"iteration":713,"passed_time":11.97133314,"remaining_time":4.795239884},
{"learn":[0.2295106244],"iteration":714,"passed_time":11.98134626,"remaining_time":4.775781375},
{"learn":[0.2294343217],"iteration":715,"passed_time":12.03788224,"remaining_time":4.774802452},
{"learn":[0.2293367022],"iteration":716,"passed_time":12.05429855,"remaining_time":4.757833318},
{"learn":[0.2292730993],"iteration":717,"passed_time":12.0972072,"remaining_time":4.751270796},
{"learn":[0.2292083296],"iteration":718,"passed_time":12.11429446,"remaining_time":4.734515638},
{"learn":[0.2291208059],"iteration":719,"passed_time":12.12659776,"remaining_time":4.715899127},
{"learn":[0.2290739985],"iteration":720,"passed_time":12.14088066,"remaining_time":4.698066164},
{"learn":[0.2290050193],"iteration":721,"passed_time":12.18711431,"remaining_time":4.6925454},
{"learn":[0.2289293059],"iteration":722,"passed_time":12.19617147,"remaining_time":4.672668738},
{"learn":[0.2288566127],"iteration":723,"passed_time":12.20466973,"remaining_time":4.652608901},
{"learn":[0.228778242],"iteration":724,"passed_time":12.21375713,"remaining_time":4.63280443},
{"learn":[0.2287350786],"iteration":725,"passed_time":12.22284979,"remaining_time":4.613031463},
{"learn":[0.2286497047],"iteration":726,"passed_time":12.23073878,"remaining_time":4.592835882},
{"learn":[0.2285686532],"iteration":727,"passed_time":12.23969614,"remaining_time":4.573073285},
{"learn":[0.2285086126],"iteration":728,"passed_time":12.2512924,"remaining_time":4.554321317},
{"learn":[0.2284110365],"iteration":729,"passed_time":12.25907295,"remaining_time":4.534177666},
{"learn":[0.2283491455],"iteration":730,"passed_time":12.26662453,"remaining_time":4.513983584},
{"learn":[0.2283074927],"iteration":731,"passed_time":12.27420532,"remaining_time":4.493834733},
{"learn":[0.2281929637],"iteration":732,"passed_time":12.2828171,"remaining_time":4.474095726},
{"learn":[0.228140413],"iteration":733,"passed_time":12.29382944,"remaining_time":4.455256989},
{"learn":[0.2280829407],"iteration":734,"passed_time":12.30226229,"remaining_time":4.435509533},
{"learn":[0.2280269703],"iteration":735,"passed_time":12.31475288,"remaining_time":4.417248316},
{"learn":[0.2279268317],"iteration":736,"passed_time":12.32235564,"remaining_time":4.397258524},
{"learn":[0.2278764426],"iteration":737,"passed_time":12.32860434,"remaining_time":4.376821595},
{"learn":[0.2277838768],"iteration":738,"passed_time":12.33714385,"remaining_time":4.357232132},
{"learn":[0.2277184406],"iteration":739,"passed_time":12.34519879,"remaining_time":4.337502277},
{"learn":[0.2276415801],"iteration":740,"passed_time":12.35231793,"remaining_time":4.317476846},
{"learn":[0.2275788136],"iteration":741,"passed_time":12.36010961,"remaining_time":4.297720053},
{"learn":[0.2274685848],"iteration":742,"passed_time":12.36764509,"remaining_time":4.277906849},
{"learn":[0.2273567791],"iteration":743,"passed_time":12.37534263,"remaining_time":4.258182409},
{"learn":[0.227290177],"iteration":744,"passed_time":12.38253732,"remaining_time":4.238318142},
{"learn":[0.2272252503],"iteration":745,"passed_time":12.39223713,"remaining_time":4.219340794},
{"learn":[0.2271093309],"iteration":746,"passed_time":12.4009339,"remaining_time":4.200048562},
{"learn":[0.2270513318],"iteration":747,"passed_time":12.40850633,"remaining_time":4.180405874},
{"learn":[0.2269821051],"iteration":748,"passed_time":12.41698084,"remaining_time":4.161097717},
{"learn":[0.2268951006],"iteration":749,"passed_time":12.42459228,"remaining_time":4.141530759},
{"learn":[0.2268577757],"iteration":750,"passed_time":12.43408949,"remaining_time":4.122620884},
{"learn":[0.2267374854],"iteration":751,"passed_time":12.44174211,"remaining_time":4.103127717},
{"learn":[0.2266545715],"iteration":752,"passed_time":12.45168722,"remaining_time":4.084417985},
{"learn":[0.2265211964],"iteration":753,"passed_time":12.46014341,"remaining_time":4.065245729},
{"learn":[0.2264418443],"iteration":754,"passed_time":12.46890435,"remaining_time":4.046200748},
{"learn":[0.2263816076],"iteration":755,"passed_time":12.47686841,"remaining_time":4.026925785},
{"learn":[0.2262709857],"iteration":756,"passed_time":12.48639355,"remaining_time":4.008181812},
{"learn":[0.2261135743],"iteration":757,"passed_time":12.49623698,"remaining_time":3.989563785},
{"learn":[0.2260265171],"iteration":758,"passed_time":12.50592495,"remaining_time":3.970919517},
{"learn":[0.2259487212],"iteration":759,"passed_time":12.51511689,"remaining_time":3.952142176},
{"learn":[0.2258194408],"iteration":760,"passed_time":12.52286424,"remaining_time":3.932936337},
{"learn":[0.2257010399],"iteration":761,"passed_time":12.52993026,"remaining_time":3.91354777},
{"learn":[0.2255895058],"iteration":762,"passed_time":12.53829885,"remaining_time":3.894596104},
{"learn":[0.2254854766],"iteration":763,"passed_time":12.54605166,"remaining_time":3.875481925},
{"learn":[0.2254323428],"iteration":764,"passed_time":12.55302643,"remaining_time":3.856158447},
{"learn":[0.2253678758],"iteration":765,"passed_time":12.56006654,"remaining_time":3.836887166},
{"learn":[0.2252679648],"iteration":766,"passed_time":12.56736933,"remaining_time":3.817727579},
{"learn":[0.2251711311],"iteration":767,"passed_time":12.57474387,"remaining_time":3.798620545},
{"learn":[0.2250901768],"iteration":768,"passed_time":12.58256451,"remaining_time":3.779678026},
{"learn":[0.2250243447],"iteration":769,"passed_time":12.59009865,"remaining_time":3.760678817},
{"learn":[0.2249088759],"iteration":770,"passed_time":12.59793695,"remaining_time":3.74179969},
{"learn":[0.2247924758],"iteration":771,"passed_time":12.60540595,"remaining_time":3.7228401},
{"learn":[0.2247571817],"iteration":772,"passed_time":12.61721935,"remaining_time":3.705186019},
{"learn":[0.2246960144],"iteration":773,"passed_time":12.62389825,"remaining_time":3.686047808},
{"learn":[0.2246403438],"iteration":774,"passed_time":12.63158887,"remaining_time":3.66723548},
{"learn":[0.2245633019],"iteration":775,"passed_time":12.63880321,"remaining_time":3.648314329},
{"learn":[0.2244798935],"iteration":776,"passed_time":12.64751403,"remaining_time":3.629852804},
{"learn":[0.2243886577],"iteration":777,"passed_time":12.65448954,"remaining_time":3.61092118},
{"learn":[0.2243161563],"iteration":778,"passed_time":12.66316252,"remaining_time":3.59250182},
{"learn":[0.224150507],"iteration":779,"passed_time":12.67091763,"remaining_time":3.573848562},
{"learn":[0.2241267481],"iteration":780,"passed_time":12.67966749,"remaining_time":3.555502151},
{"learn":[0.2240438192],"iteration":781,"passed_time":12.6869523,"remaining_time":3.536771868},
{"learn":[0.2239361936],"iteration":782,"passed_time":12.69498314,"remaining_time":3.518277575},
{"learn":[0.2238129261],"iteration":783,"passed_time":12.70294289,"remaining_time":3.499790388},
{"learn":[0.2237008513],"iteration":784,"passed_time":12.7125258,"remaining_time":3.481774581},
{"learn":[0.2236356845],"iteration":785,"passed_time":12.72192202,"remaining_time":3.463729406},
{"learn":[0.2235859985],"iteration":786,"passed_time":12.73018446,"remaining_time":3.445399351},
{"learn":[0.2235286876],"iteration":787,"passed_time":12.73913106,"remaining_time":3.427278915},
{"learn":[0.2234387724],"iteration":788,"passed_time":12.74692268,"remaining_time":3.408872858},
{"learn":[0.2233471629],"iteration":789,"passed_time":12.75585713,"remaining_time":3.390797465},
{"learn":[0.2232848582],"iteration":790,"passed_time":12.76424185,"remaining_time":3.372599933},
{"learn":[0.2232325218],"iteration":791,"passed_time":12.77313968,"remaining_time":3.354561936},
{"learn":[0.2231196845],"iteration":792,"passed_time":12.78048415,"remaining_time":3.336141513},
{"learn":[0.2230741163],"iteration":793,"passed_time":12.78970369,"remaining_time":3.318235466},
{"learn":[0.2230172167],"iteration":794,"passed_time":12.79799415,"remaining_time":3.3001117},
{"learn":[0.2229076009],"iteration":795,"passed_time":12.80677259,"remaining_time":3.282137699},
{"learn":[0.2228355933],"iteration":796,"passed_time":12.81480054,"remaining_time":3.26399562},
{"learn":[0.2227757414],"iteration":797,"passed_time":12.82404791,"remaining_time":3.246187566},
{"learn":[0.2226861279],"iteration":798,"passed_time":12.83154706,"remaining_time":3.227961151},
{"learn":[0.2226054548],"iteration":799,"passed_time":12.84023811,"remaining_time":3.210059527},
{"learn":[0.2225568033],"iteration":800,"passed_time":12.84779517,"remaining_time":3.191899175},
{"learn":[0.222485539],"iteration":801,"passed_time":12.86334625,"remaining_time":3.175738849},
{"learn":[0.2224039336],"iteration":802,"passed_time":12.89229023,"remaining_time":3.162865722},
{"learn":[0.222317027],"iteration":803,"passed_time":12.90580434,"remaining_time":3.146191109},
{"learn":[0.2222256346],"iteration":804,"passed_time":12.9206006,"remaining_time":3.129834929},
{"learn":[0.2221488182],"iteration":805,"passed_time":12.9370842,"remaining_time":3.113888754},
{"learn":[0.2220396183],"iteration":806,"passed_time":12.96363337,"remaining_time":3.100348501},
{"learn":[0.2219970165],"iteration":807,"passed_time":12.98608081,"remaining_time":3.08580138},
{"learn":[0.2219473343],"iteration":808,"passed_time":13.01343138,"remaining_time":3.072392329},
{"learn":[0.2218610333],"iteration":809,"passed_time":13.03606027,"remaining_time":3.057841299},
{"learn":[0.2217705349],"iteration":810,"passed_time":13.05955334,"remaining_time":3.04347174},
{"learn":[0.2216902132],"iteration":811,"passed_time":13.07843092,"remaining_time":3.028011099},
{"learn":[0.2216198402],"iteration":812,"passed_time":13.09450356,"remaining_time":3.011896883},
{"learn":[0.2215000553],"iteration":813,"passed_time":13.11252194,"remaining_time":2.996227372},
{"learn":[0.2214210088],"iteration":814,"passed_time":13.13725871,"remaining_time":2.98207713},
{"learn":[0.2213145134],"iteration":815,"passed_time":13.18093022,"remaining_time":2.97217054},
{"learn":[0.2212563945],"iteration":816,"passed_time":13.2435285,"remaining_time":2.966420704},
{"learn":[0.2211948198],"iteration":817,"passed_time":13.2572536,"remaining_time":2.949657891},
{"learn":[0.2211018906],"iteration":818,"passed_time":13.27058991,"remaining_time":2.932816573},
{"learn":[0.2210395671],"iteration":819,"passed_time":13.28040844,"remaining_time":2.915211608},
{"learn":[0.2209816428],"iteration":820,"passed_time":13.28933702,"remaining_time":2.89743158},
{"learn":[0.2208975366],"iteration":821,"passed_time":13.2972828,"remaining_time":2.879460266},
{"learn":[0.2207876028],"iteration":822,"passed_time":13.32966414,"remaining_time":2.866768594},
{"learn":[0.2207006007],"iteration":823,"passed_time":13.45335353,"remaining_time":2.873531822},
{"learn":[0.2205683991],"iteration":824,"passed_time":13.49668785,"remaining_time":2.862933786},
{"learn":[0.2205182451],"iteration":825,"passed_time":13.51890779,"remaining_time":2.847808664},
{"learn":[0.2204321364],"iteration":826,"passed_time":13.54633835,"remaining_time":2.83375639},
{"learn":[0.2203238732],"iteration":827,"passed_time":13.57094471,"remaining_time":2.819085134},
{"learn":[0.2201951611],"iteration":828,"passed_time":13.59005266,"remaining_time":2.803255736},
{"learn":[0.2201394317],"iteration":829,"passed_time":13.61056938,"remaining_time":2.787706982},
{"learn":[0.2200474832],"iteration":830,"passed_time":13.63288894,"remaining_time":2.772512913},
{"learn":[0.21997529],"iteration":831,"passed_time":13.64638799,"remaining_time":2.755520652},
{"learn":[0.2199251369],"iteration":832,"passed_time":13.65421276,"remaining_time":2.737399196},
{"learn":[0.2198482482],"iteration":833,"passed_time":13.66362463,"remaining_time":2.719618332},
{"learn":[0.2197564679],"iteration":834,"passed_time":13.67055181,"remaining_time":2.701366525},
{"learn":[0.2196673308],"iteration":835,"passed_time":13.68328602,"remaining_time":2.684280991},
{"learn":[0.2195727369],"iteration":836,"passed_time":13.71057609,"remaining_time":2.670040505},
{"learn":[0.2195267991],"iteration":837,"passed_time":13.72484475,"remaining_time":2.653251611},
{"learn":[0.2194165037],"iteration":838,"passed_time":13.73725368,"remaining_time":2.63611185},
{"learn":[0.2193365336],"iteration":839,"passed_time":13.74601701,"remaining_time":2.618288955},
{"learn":[0.219256156],"iteration":840,"passed_time":13.75329082,"remaining_time":2.600205993},
{"learn":[0.2191820488],"iteration":841,"passed_time":13.76755687,"remaining_time":2.58346079},
{"learn":[0.219078283],"iteration":842,"passed_time":13.78727713,"remaining_time":2.567737259},
{"learn":[0.2189887547],"iteration":843,"passed_time":13.80163315,"remaining_time":2.551012763},
{"learn":[0.2189045014],"iteration":844,"passed_time":13.82206037,"remaining_time":2.535407523},
{"learn":[0.2187976851],"iteration":845,"passed_time":13.83165003,"remaining_time":2.51781809},
{"learn":[0.2187240409],"iteration":846,"passed_time":13.84076772,"remaining_time":2.500162292},
{"learn":[0.2186128902],"iteration":847,"passed_time":13.85354447,"remaining_time":2.4831825},
{"learn":[0.2185590934],"iteration":848,"passed_time":13.86122502,"remaining_time":2.465306216},
{"learn":[0.218495048],"iteration":849,"passed_time":13.86871584,"remaining_time":2.447420442},
{"learn":[0.2183952059],"iteration":850,"passed_time":13.88146976,"remaining_time":2.430480604},
{"learn":[0.218282671],"iteration":851,"passed_time":13.89153134,"remaining_time":2.413082908},
{"learn":[0.2182229554],"iteration":852,"passed_time":13.89856856,"remaining_time":2.395181217},
{"learn":[0.218177822],"iteration":853,"passed_time":13.90807087,"remaining_time":2.377726402},
{"learn":[0.2181459294],"iteration":854,"passed_time":13.91451144,"remaining_time":2.359770947},
{"learn":[0.218099682],"iteration":855,"passed_time":13.9218572,"remaining_time":2.341994669},
{"learn":[0.2180083072],"iteration":856,"passed_time":13.9281654,"remaining_time":2.324069607},
{"learn":[0.2179016735],"iteration":857,"passed_time":13.93396777,"remaining_time":2.306087906},
{"learn":[0.2177996897],"iteration":858,"passed_time":13.94110986,"remaining_time":2.28835447},
{"learn":[0.2177339565],"iteration":859,"passed_time":13.94724992,"remaining_time":2.270482545},
{"learn":[0.2176328451],"iteration":860,"passed_time":13.95472977,"remaining_time":2.252854167},
{"learn":[0.2175207106],"iteration":861,"passed_time":13.96167925,"remaining_time":2.235164428},
{"learn":[0.217391221],"iteration":862,"passed_time":13.97155298,"remaining_time":2.217963799},
{"learn":[0.2172997121],"iteration":863,"passed_time":13.97824077,"remaining_time":2.20027864},
{"learn":[0.2172812099],"iteration":864,"passed_time":13.98508956,"remaining_time":2.182644035},
{"learn":[0.2171897308],"iteration":865,"passed_time":13.99206537,"remaining_time":2.165053995},
{"learn":[0.2171592882],"iteration":866,"passed_time":13.99869544,"remaining_time":2.147435402},
{"learn":[0.2170711137],"iteration":867,"passed_time":14.00578651,"remaining_time":2.129912235},
{"learn":[0.2169964425],"iteration":868,"passed_time":14.01267502,"remaining_time":2.11238254},
{"learn":[0.2169123763],"iteration":869,"passed_time":14.02164266,"remaining_time":2.095187984},
{"learn":[0.2168527044],"iteration":870,"passed_time":14.02817677,"remaining_time":2.077651899},
{"learn":[0.2167630187],"iteration":871,"passed_time":14.03523957,"remaining_time":2.060218652},
{"learn":[0.2166542963],"iteration":872,"passed_time":14.04105139,"remaining_time":2.042627178},
{"learn":[0.2165674552],"iteration":873,"passed_time":14.04865893,"remaining_time":2.02532154},
{"learn":[0.2164746902],"iteration":874,"passed_time":14.05715117,"remaining_time":2.008164454},
{"learn":[0.2163904261],"iteration":875,"passed_time":14.06666457,"remaining_time":1.991171698},
{"learn":[0.2162828722],"iteration":876,"passed_time":14.07406342,"remaining_time":1.973899431},
{"learn":[0.2161993541],"iteration":877,"passed_time":14.08222865,"remaining_time":1.956756145},
{"learn":[0.2161043175],"iteration":878,"passed_time":14.08826912,"remaining_time":1.939340801},
{"learn":[0.2160321225],"iteration":879,"passed_time":14.09477544,"remaining_time":1.922014833},
{"learn":[0.2158813847],"iteration":880,"passed_time":14.10192248,"remaining_time":1.904799971},
{"learn":[0.2157993991],"iteration":881,"passed_time":14.1102269,"remaining_time":1.887762782},
{"learn":[0.2156964776],"iteration":882,"passed_time":14.13203665,"remaining_time":1.872534867},
{"learn":[0.2156407433],"iteration":883,"passed_time":14.14021005,"remaining_time":1.855502676},
{"learn":[0.2155733927],"iteration":884,"passed_time":14.14869084,"remaining_time":1.838530448},
{"learn":[0.2154885765],"iteration":885,"passed_time":14.15673981,"remaining_time":1.821521826},
{"learn":[0.2153875011],"iteration":886,"passed_time":14.16351614,"remaining_time":1.804371278},
{"learn":[0.2153104712],"iteration":887,"passed_time":14.16983163,"remaining_time":1.787185971},
{"learn":[0.2152245006],"iteration":888,"passed_time":14.17565706,"remaining_time":1.76996393},
{"learn":[0.2151279499],"iteration":889,"passed_time":14.182323,"remaining_time":1.752871382},
{"learn":[0.2150468593],"iteration":890,"passed_time":14.18847588,"remaining_time":1.735739473},
{"learn":[0.2149907758],"iteration":891,"passed_time":14.19529511,"remaining_time":1.718712861},
{"learn":[0.2148998205],"iteration":892,"passed_time":14.2008528,"remaining_time":1.701557951},
{"learn":[0.214817667],"iteration":893,"passed_time":14.20883004,"remaining_time":1.684715866},
{"learn":[0.2147312873],"iteration":894,"passed_time":14.21502222,"remaining_time":1.667684171},
{"learn":[0.2146510052],"iteration":895,"passed_time":14.22111366,"remaining_time":1.650664978},
{"learn":[0.2145801884],"iteration":896,"passed_time":14.22735861,"remaining_time":1.633687778},
{"learn":[0.2144755447],"iteration":897,"passed_time":14.23313149,"remaining_time":1.61668086},
{"learn":[0.2144273462],"iteration":898,"passed_time":14.24563691,"remaining_time":1.600455314},
{"learn":[0.2143466117],"iteration":899,"passed_time":14.25269364,"remaining_time":1.583632627},
{"learn":[0.2142605823],"iteration":900,"passed_time":14.26075704,"remaining_time":1.566942227},
{"learn":[0.2141757593],"iteration":901,"passed_time":14.26688774,"remaining_time":1.550060974},
{"learn":[0.2140860105],"iteration":902,"passed_time":14.27280027,"remaining_time":1.533180096},
{"learn":[0.2140317727],"iteration":903,"passed_time":14.27946009,"remaining_time":1.516402841},
{"learn":[0.2139360698],"iteration":904,"passed_time":14.28617877,"remaining_time":1.499654125},
{"learn":[0.2138676125],"iteration":905,"passed_time":14.29390553,"remaining_time":1.483032141},
{"learn":[0.2137737967],"iteration":906,"passed_time":14.30037859,"remaining_time":1.466301223},
{"learn":[0.2137013105],"iteration":907,"passed_time":14.30748329,"remaining_time":1.449656897},
{"learn":[0.2136350456],"iteration":908,"passed_time":14.31347891,"remaining_time":1.432922531},
{"learn":[0.2135866104],"iteration":909,"passed_time":14.31925079,"remaining_time":1.416189639},
{"learn":[0.2135356458],"iteration":910,"passed_time":14.32551043,"remaining_time":1.399528461},
{"learn":[0.2134045515],"iteration":911,"passed_time":14.33108715,"remaining_time":1.382824199},
{"learn":[0.2133569294],"iteration":912,"passed_time":14.33686288,"remaining_time":1.366163275},
{"learn":[0.2133210339],"iteration":913,"passed_time":14.34344968,"remaining_time":1.349602486},
{"learn":[0.2132186855],"iteration":914,"passed_time":14.34921249,"remaining_time":1.332986952},
{"learn":[0.2130816344],"iteration":915,"passed_time":14.35726709,"remaining_time":1.316605279},
{"learn":[0.2130001185],"iteration":916,"passed_time":14.36336377,"remaining_time":1.300064551},
{"learn":[0.2129173914],"iteration":917,"passed_time":14.36926973,"remaining_time":1.283529541},
{"learn":[0.2128151532],"iteration":918,"passed_time":14.37584854,"remaining_time":1.267076966},
{"learn":[0.2127634934],"iteration":919,"passed_time":14.38154336,"remaining_time":1.250568988},
{"learn":[0.2126532184],"iteration":920,"passed_time":14.38807609,"remaining_time":1.234156364},
{"learn":[0.2125886589],"iteration":921,"passed_time":14.3937171,"remaining_time":1.217689733},
{"learn":[0.2125217763],"iteration":922,"passed_time":14.39903216,"remaining_time":1.201219368},
{"learn":[0.2124277015],"iteration":923,"passed_time":14.40756664,"remaining_time":1.185037949},
{"learn":[0.2123920186],"iteration":924,"passed_time":14.41323528,"remaining_time":1.168640698},
{"learn":[0.2123283015],"iteration":925,"passed_time":14.41926798,"remaining_time":1.152295714},
{"learn":[0.2122868067],"iteration":926,"passed_time":14.42471663,"remaining_time":1.135926984},
{"learn":[0.212207656],"iteration":927,"passed_time":14.43037549,"remaining_time":1.119598099},
{"learn":[0.2121530996],"iteration":928,"passed_time":14.43664999,"remaining_time":1.103339235},
{"learn":[0.2121003427],"iteration":929,"passed_time":14.44197162,"remaining_time":1.087030122},
{"learn":[0.2120773476],"iteration":930,"passed_time":14.44774176,"remaining_time":1.070777853},
{"learn":[0.2119914567],"iteration":931,"passed_time":14.45435442,"remaining_time":1.05460955},
{"learn":[0.2119181607],"iteration":932,"passed_time":14.45983533,"remaining_time":1.038380458},
{"learn":[0.2118343648],"iteration":933,"passed_time":14.46582184,"remaining_time":1.022210109},
{"learn":[0.2117476504],"iteration":934,"passed_time":14.47347546,"remaining_time":1.006177438},
{"learn":[0.211671864],"iteration":935,"passed_time":14.47974968,"remaining_time":0.9900683539},
{"learn":[0.2115634375],"iteration":936,"passed_time":14.48666054,"remaining_time":0.9740230671},
{"learn":[0.2114921494],"iteration":937,"passed_time":14.49197677,"remaining_time":0.957891855},
{"learn":[0.2114446228],"iteration":938,"passed_time":14.49780083,"remaining_time":0.9418166675},
{"learn":[0.2113806144],"iteration":939,"passed_time":14.50385297,"remaining_time":0.9257778495},
{"learn":[0.2113313698],"iteration":940,"passed_time":14.51058362,"remaining_time":0.9098027986},
{"learn":[0.2112281193],"iteration":941,"passed_time":14.5169307,"remaining_time":0.8938237588},
{"learn":[0.2111363277],"iteration":942,"passed_time":14.52263828,"remaining_time":0.8778264921},
{"learn":[0.2110381304],"iteration":943,"passed_time":14.52819727,"remaining_time":0.8618422106},
{"learn":[0.2110040217],"iteration":944,"passed_time":14.53424159,"remaining_time":0.8459082409},
{"learn":[0.2109336805],"iteration":945,"passed_time":14.53988371,"remaining_time":0.8299722202},
{"learn":[0.2108535422],"iteration":946,"passed_time":14.54530729,"remaining_time":0.814045709},
{"learn":[0.2107796586],"iteration":947,"passed_time":14.55134703,"remaining_time":0.7981751535},
{"learn":[0.2107322103],"iteration":948,"passed_time":14.55691949,"remaining_time":0.7823002042},
{"learn":[0.2106380942],"iteration":949,"passed_time":14.56601359,"remaining_time":0.7666322942},
{"learn":[0.2105750984],"iteration":950,"passed_time":14.57207489,"remaining_time":0.7508219451},
{"learn":[0.2105587521],"iteration":951,"passed_time":14.57778783,"remaining_time":0.7350145124},
{"learn":[0.2104796711],"iteration":952,"passed_time":14.58430268,"remaining_time":0.7192678132},
{"learn":[0.2104354183],"iteration":953,"passed_time":14.59028885,"remaining_time":0.7035149761},
{"learn":[0.2102888874],"iteration":954,"passed_time":14.59774668,"remaining_time":0.6878519377},
{"learn":[0.2102272073],"iteration":955,"passed_time":14.60382122,"remaining_time":0.6721423994},
{"learn":[0.2101609015],"iteration":956,"passed_time":14.6094416,"remaining_time":0.65643259},
{"learn":[0.2101186392],"iteration":957,"passed_time":14.61620639,"remaining_time":0.6407940169},
{"learn":[0.2100623684],"iteration":958,"passed_time":14.62378223,"remaining_time":0.6252086249},
{"learn":[0.2099852071],"iteration":959,"passed_time":14.63100183,"remaining_time":0.6096250761},
{"learn":[0.209931576],"iteration":960,"passed_time":14.636504,"remaining_time":0.5939892362},
{"learn":[0.2098778906],"iteration":961,"passed_time":14.64231493,"remaining_time":0.5783866605},
{"learn":[0.2098212108],"iteration":962,"passed_time":14.64860233,"remaining_time":0.562822727},
{"learn":[0.2097355904],"iteration":963,"passed_time":14.65449999,"remaining_time":0.5472634851},
{"learn":[0.2096675565],"iteration":964,"passed_time":14.66489511,"remaining_time":0.5318873873},
{"learn":[0.2095786562],"iteration":965,"passed_time":14.67495051,"remaining_time":0.5165096453},
{"learn":[0.2094775999],"iteration":966,"passed_time":14.68166944,"remaining_time":0.50102905},
{"learn":[0.2094124806],"iteration":967,"passed_time":14.68885411,"remaining_time":0.4855819539},
{"learn":[0.2093137199],"iteration":968,"passed_time":14.6966005,"remaining_time":0.4701698817},
{"learn":[0.2092731325],"iteration":969,"passed_time":14.70256868,"remaining_time":0.4547186189},
{"learn":[0.2091795476],"iteration":970,"passed_time":14.7098369,"remaining_time":0.4393257157},
{"learn":[0.2090833485],"iteration":971,"passed_time":14.71714616,"remaining_time":0.4239507125},
{"learn":[0.2090221253],"iteration":972,"passed_time":14.72390067,"remaining_time":0.4085768941},
{"learn":[0.2089916735],"iteration":973,"passed_time":14.73052804,"remaining_time":0.3932173809},
{"learn":[0.2089134964],"iteration":974,"passed_time":14.7366846,"remaining_time":0.3778637077},
{"learn":[0.2088754638],"iteration":975,"passed_time":14.74496324,"remaining_time":0.3625810634},
{"learn":[0.2088181758],"iteration":976,"passed_time":14.75350131,"remaining_time":0.347318864},
{"learn":[0.2087316225],"iteration":977,"passed_time":14.76392706,"remaining_time":0.3321128785},
{"learn":[0.2086518093],"iteration":978,"passed_time":14.77002479,"remaining_time":0.3168238209},
{"learn":[0.2085896408],"iteration":979,"passed_time":14.77783304,"remaining_time":0.3015884294},
{"learn":[0.2085149114],"iteration":980,"passed_time":14.78537743,"remaining_time":0.2863630694},
{"learn":[0.2084681313],"iteration":981,"passed_time":14.79408326,"remaining_time":0.2711746422},
{"learn":[0.2084018793],"iteration":982,"passed_time":14.80083638,"remaining_time":0.2559656342},
{"learn":[0.2083117255],"iteration":983,"passed_time":14.81059307,"remaining_time":0.2408226515},
{"learn":[0.2082109559],"iteration":984,"passed_time":14.81918328,"remaining_time":0.2256728418},
{"learn":[0.2080833051],"iteration":985,"passed_time":14.82623847,"remaining_time":0.2105145422},
{"learn":[0.2079705554],"iteration":986,"passed_time":14.83223678,"remaining_time":0.1953587417},
{"learn":[0.2078745753],"iteration":987,"passed_time":14.83791079,"remaining_time":0.18021754},
{"learn":[0.2077955334],"iteration":988,"passed_time":14.84462544,"remaining_time":0.1651070574},
{"learn":[0.2077184245],"iteration":989,"passed_time":14.85038668,"remaining_time":0.1500039059},
{"learn":[0.2076516549],"iteration":990,"passed_time":14.85733278,"remaining_time":0.1349303683},
{"learn":[0.2075784212],"iteration":991,"passed_time":14.86315871,"remaining_time":0.1198641831},
{"learn":[0.2075384721],"iteration":992,"passed_time":14.86896317,"remaining_time":0.1048164574},
{"learn":[0.2074585229],"iteration":993,"passed_time":14.87503549,"remaining_time":0.0897889466},
{"learn":[0.2073760011],"iteration":994,"passed_time":14.88070497,"remaining_time":0.0747774119},
{"learn":[0.2072925473],"iteration":995,"passed_time":14.88676317,"remaining_time":0.05978619746},
{"learn":[0.20719592],"iteration":996,"passed_time":14.89227302,"remaining_time":0.04481125283},
{"learn":[0.2071256886],"iteration":997,"passed_time":14.89802472,"remaining_time":0.02985576096},
{"learn":[0.2070441865],"iteration":998,"passed_time":14.90459864,"remaining_time":0.01491951816},
{"learn":[0.2069738704],"iteration":999,"passed_time":14.91078812,"remaining_time":0}
]}passed_time":15.1463024,"remaining_time":0}
]}